[
  {
    "images": {
      "large": "https://cdn.myanimelist.net/images/anime/1347/151708l.jpg",
      "medium": "https://cdn.myanimelist.net/images/anime/1347/151708.jpg"
    },
    "title": "Cat's\u2665Eye",
    "title_english": "",
    "num_episodes": 12,
    "score": 6.58,
    "streams": null,
    "episode": "2",
    "karma": 48,
    "comments": 34,
    "week_id": 2,
    "studio": [
      "LIDENFILMS"
    ],
    "url": "https://www.reddit.com/r/anime/comments/1nws92q/catseye_cats_eye_episode_2_discussion/",
    "mal_id": 60347,
    "current_rank": 1,
    "karma_change": -54,
    "rank_change": 28,
    "season": "fall"
  }
]