[
  {
    "images": {
      "large": "https://cdn.myanimelist.net/images/anime/1214/142185l.jpg",
      "medium": "https://cdn.myanimelist.net/images/anime/1214/142185.jpg"
    },
    "num_episodes": 13,
    "score": null,
    "streams": null,
    "title": "Haigakura",
    "title_english": "",
    "episode": "10",
    "karma": 8,
    "comments": 2,
    "week_id": 11,
    "studio": [
      "Typhoon Graphics"
    ],
    "url": "https://www.reddit.com/r/anime/comments/1n91deg/haigakura_episode_10_discussion/",
    "mal_id": 56420,
    "current_rank": 1,
    "karma_change": 2,
    "rank_change": 66,
    "season": "summer"
  }
]