[
  {
    "images": {
      "large": "https://cdn.myanimelist.net/images/anime/1887/150496l.jpg",
      "medium": "https://cdn.myanimelist.net/images/anime/1887/150496.jpg"
    },
    "title": "Watashi ga Koibito ni Nareru Wake Nai jan, Muri Muri! (\u203bMuri ja Nakatta!?)",
    "title_english": "There's No Freaking Way I'll be Your Lover! Unless...",
    "num_episodes": 0,
    "score": 7.65,
    "streams": null,
    "banner": {
      "url": "https://media1.tenor.com/m/xaCA0NRrdk8AAAAC/watanare-oozuka-mai.gif",
      "offset": "-2px -17px"
    },
    "episode": "4",
    "karma": 1849,
    "comments": 461,
    "week_id": 5,
    "studio": [
      "studio MOTHER"
    ],
    "url": "https://www.reddit.com/r/anime/comments/1mbl7vs/watashi_ga_koibito_ni_nareru_wake_nai_jan_muri/",
    "mal_id": 60326,
    "current_rank": 1,
    "karma_change": -133,
    "rank_change": 2,
    "season": "summer"
  },
  {
    "images": {
      "large": "https://cdn.myanimelist.net/images/anime/1024/150787l.jpg",
      "medium": "https://cdn.myanimelist.net/images/anime/1024/150787.jpg"
    },
    "title": "Sono Bisque Doll wa Koi wo Suru Season 2",
    "title_english": "My Dress-Up Darling Season 2",
    "num_episodes": 0,
    "score": 8.42,
    "streams": null,
    "episode": "4",
    "karma": 1846,
    "comments": 342,
    "week_id": 5,
    "studio": [
      "CloverWorks"
    ],
    "url": "https://www.reddit.com/r/anime/comments/1m9xpet/sono_bisque_doll_wa_koi_wo_suru_season_2_my/",
    "mal_id": 53065,
    "current_rank": 2,
    "karma_change": -295,
    "rank_change": 0,
    "season": "summer"
  },
  {
    "images": {
      "large": "https://cdn.myanimelist.net/images/anime/1182/149879l.jpg",
      "medium": "https://cdn.myanimelist.net/images/anime/1182/149879.jpg"
    },
    "title": "Takopii no Genzai",
    "title_english": "Takopi's Original Sin",
    "num_episodes": 6,
    "score": null,
    "streams": null,
    "episode": "5",
    "karma": 1703,
    "comments": 941,
    "week_id": 5,
    "studio": [
      "Enishiya"
    ],
    "url": "https://www.reddit.com/r/anime/comments/1m91nuv/takopii_no_genzai_takopis_original_sin_episode_5/",
    "mal_id": 60489,
    "current_rank": 3,
    "karma_change": 228,
    "rank_change": 2,
    "season": "summer"
  },
  {
    "images": {
      "large": "https://cdn.myanimelist.net/images/anime/1669/149732l.jpg",
      "medium": "https://cdn.myanimelist.net/images/anime/1669/149732.jpg"
    },
    "title": "Silent Witch: Chinmoku no Majo no Kakushigoto",
    "title_english": "Secrets of the Silent Witch",
    "num_episodes": 0,
    "score": 7.94,
    "streams": null,
    "episode": "4",
    "karma": 1495,
    "comments": 331,
    "week_id": 5,
    "studio": [
      "Studio Gokumi"
    ],
    "url": "https://www.reddit.com/r/anime/comments/1m93vlh/silent_witch_chinmoku_no_majo_no_kakushigoto/",
    "mal_id": 59459,
    "current_rank": 4,
    "karma_change": 66,
    "rank_change": 3,
    "season": "summer"
  },
  {
    "images": {
      "large": "https://cdn.myanimelist.net/images/anime/1682/150432l.jpg",
      "medium": "https://cdn.myanimelist.net/images/anime/1682/150432.jpg"
    },
    "title": "Gachiakuta",
    "title_english": "Gachiakuta",
    "num_episodes": 0,
    "score": 8.08,
    "streams": null,
    "episode": "3",
    "karma": 1489,
    "comments": 227,
    "week_id": 5,
    "studio": [
      "Bones Film"
    ],
    "url": "https://www.reddit.com/r/anime/comments/1maojjs/gachiakuta_episode_3_discussion/",
    "mal_id": 59062,
    "current_rank": 5,
    "karma_change": 0,
    "rank_change": "returning",
    "season": "summer"
  },
  {
    "images": {
      "large": "https://cdn.myanimelist.net/images/anime/1255/150593l.jpg",
      "medium": "https://cdn.myanimelist.net/images/anime/1255/150593.jpg"
    },
    "title": "Clevatess: Majuu no Ou to Akago to Shikabane no Yuusha",
    "title_english": "Clevatess",
    "num_episodes": 12,
    "score": 7.91,
    "streams": null,
    "episode": "5",
    "karma": 1366,
    "comments": 324,
    "week_id": 5,
    "studio": [
      "Lay-duce"
    ],
    "url": "https://www.reddit.com/r/anime/comments/1md48hd/clevatess_majuu_no_ou_to_akago_to_shikabane_no/",
    "mal_id": 59205,
    "current_rank": 6,
    "karma_change": -188,
    "rank_change": -2,
    "season": "summer"
  },
  {
    "images": {
      "large": "https://cdn.myanimelist.net/images/anime/1104/148614l.jpg",
      "medium": "https://cdn.myanimelist.net/images/anime/1104/148614.jpg"
    },
    "title": "Hikaru ga Shinda Natsu",
    "title_english": "The Summer Hikaru Died",
    "num_episodes": 12,
    "score": 8.21,
    "streams": null,
    "episode": "4",
    "karma": 1193,
    "comments": 262,
    "week_id": 5,
    "studio": [
      "CygamesPictures"
    ],
    "url": "https://www.reddit.com/r/anime/comments/1m9yiyb/hikaru_ga_shinda_natsu_the_summer_hikaru_died/",
    "mal_id": 58913,
    "current_rank": 7,
    "karma_change": -277,
    "rank_change": -1,
    "season": "summer"
  },
  {
    "images": {
      "large": "https://cdn.myanimelist.net/images/anime/1509/148453l.jpg",
      "medium": "https://cdn.myanimelist.net/images/anime/1509/148453.jpg"
    },
    "title": "Yofukashi no Uta Season 2",
    "title_english": "Call of the Night Season 2",
    "num_episodes": 0,
    "score": 8.23,
    "streams": null,
    "episode": "4",
    "karma": 1160,
    "comments": 186,
    "week_id": 5,
    "studio": [
      "LIDENFILMS"
    ],
    "url": "https://www.reddit.com/r/anime/comments/1m91nvj/yofukashi_no_uta_season_2_call_of_the_night/",
    "mal_id": 58390,
    "current_rank": 8,
    "karma_change": 22,
    "rank_change": 2,
    "season": "summer"
  },
  {
    "images": {
      "large": "https://cdn.myanimelist.net/images/anime/1744/150433l.jpg",
      "medium": "https://cdn.myanimelist.net/images/anime/1744/150433.jpg"
    },
    "title": "Kaoru Hana wa Rin to Saku",
    "title_english": "The Fragrant Flower Blooms with Dignity",
    "num_episodes": 13,
    "score": 8.78,
    "streams": null,
    "episode": "4",
    "karma": 1019,
    "comments": 152,
    "week_id": 5,
    "studio": [
      "CloverWorks"
    ],
    "url": "https://www.reddit.com/r/anime/comments/1maded4/kaoru_hana_wa_rin_to_saku_the_fragrant_flower/",
    "mal_id": 59845,
    "current_rank": 9,
    "karma_change": -127,
    "rank_change": 0,
    "season": "summer"
  },
  {
    "images": {
      "large": "https://cdn.myanimelist.net/images/anime/1177/150344l.jpg",
      "medium": "https://cdn.myanimelist.net/images/anime/1177/150344.jpg"
    },
    "title": "Kaijuu 8-gou 2nd Season",
    "title_english": "Kaiju No. 8 Season 2",
    "num_episodes": 0,
    "score": 7.95,
    "streams": null,
    "episode": "2",
    "karma": 1015,
    "comments": 363,
    "week_id": 5,
    "studio": [
      "Production I.G"
    ],
    "url": "https://www.reddit.com/r/anime/comments/1m9uwyf/kaijuu_8gou_season_2_kaiju_no_8_season_2_episode/",
    "mal_id": 59177,
    "current_rank": 10,
    "karma_change": -330,
    "rank_change": -2,
    "season": "summer"
  },
  {
    "images": {
      "large": "https://cdn.myanimelist.net/images/anime/1108/150583l.jpg",
      "medium": "https://cdn.myanimelist.net/images/anime/1108/150583.jpg"
    },
    "title": "Grand Blue Season 2",
    "title_english": "Grand Blue Dreaming Season 2",
    "num_episodes": 0,
    "score": 8.73,
    "streams": null,
    "episode": "4",
    "karma": 969,
    "comments": 77,
    "week_id": 5,
    "studio": [
      "Zero-G",
      "Liber"
    ],
    "url": "https://www.reddit.com/r/anime/comments/1mbl215/grand_blue_season_2_grand_blue_dreaming_season_2/",
    "mal_id": 59986,
    "current_rank": 11,
    "karma_change": -132,
    "rank_change": 0,
    "season": "summer"
  },
  {
    "images": {
      "large": "https://cdn.myanimelist.net/images/anime/1823/149858l.jpg",
      "medium": "https://cdn.myanimelist.net/images/anime/1823/149858.jpg"
    },
    "title": "Seishun Buta Yarou wa Santa Claus no Yume wo Minai",
    "title_english": "Rascal Does Not Dream of Santa Claus",
    "num_episodes": 0,
    "score": 8.38,
    "streams": null,
    "episode": "4",
    "karma": 861,
    "comments": 96,
    "week_id": 5,
    "studio": [
      "CloverWorks"
    ],
    "url": "https://www.reddit.com/r/anime/comments/1m9x1jw/seishun_buta_yarou_wa_santa_claus_no_yume_wo/",
    "mal_id": 57433,
    "current_rank": 12,
    "karma_change": -72,
    "rank_change": 2,
    "season": "summer"
  },
  {
    "images": {
      "large": "https://cdn.myanimelist.net/images/anime/1981/149640l.jpg",
      "medium": "https://cdn.myanimelist.net/images/anime/1981/149640.jpg"
    },
    "title": "City The Animation",
    "title_english": "",
    "num_episodes": 0,
    "score": 7.81,
    "streams": null,
    "episode": "4",
    "karma": 857,
    "comments": 109,
    "week_id": 5,
    "studio": [
      "Kyoto Animation"
    ],
    "url": "https://www.reddit.com/r/anime/comments/1mapafm/city_the_animation_episode_4_discussion/",
    "mal_id": 59898,
    "current_rank": 13,
    "karma_change": -104,
    "rank_change": 0,
    "season": "summer"
  },
  {
    "images": {
      "large": "https://cdn.myanimelist.net/images/anime/1988/148017l.webp",
      "medium": "https://cdn.myanimelist.net/images/anime/1988/148017.webp"
    },
    "num_episodes": 0,
    "score": 7.46,
    "streams": {
      "name": "crunchyroll",
      "url": "https://www.crunchyroll.com/pt-br/series/G5PHNM9P0/witch-watch",
      "logo": "https://1000logos.net/wp-content/uploads/2021/05/Crunchyroll-Logo-2018.png"
    },
    "title": "Witch Watch",
    "title_english": "Witch Watch",
    "episode": "17",
    "karma": 732,
    "comments": 108,
    "week_id": 5,
    "studio": [
      "Bibury Animation Studios"
    ],
    "url": "https://www.reddit.com/r/anime/comments/1mah92j/witch_watch_episode_17_discussion/",
    "mal_id": 59597,
    "current_rank": 14,
    "karma_change": 13,
    "rank_change": 1,
    "season": "summer"
  },
  {
    "images": {
      "large": "https://cdn.myanimelist.net/images/anime/1154/149614l.jpg",
      "medium": "https://cdn.myanimelist.net/images/anime/1154/149614.jpg"
    },
    "title": "Tensei shitara Dainana Ouji Datta node, Kimama ni Majutsu wo Kiwamemasu 2nd Season",
    "title_english": "I Was Reincarnated as the 7th Prince so I Can Take My Time Perfecting My Magical Ability Season 2",
    "num_episodes": 0,
    "score": 7.64,
    "streams": null,
    "episode": "4",
    "karma": 634,
    "comments": 82,
    "week_id": 5,
    "studio": [
      "Tsumugi Akita Animation Lab"
    ],
    "url": "https://www.reddit.com/r/anime/comments/1md9uuq/tensei_shitara_dainana_ouji_datta_node_kimama_ni/",
    "mal_id": 59095,
    "current_rank": 15,
    "karma_change": 28,
    "rank_change": 4,
    "season": "summer"
  },
  {
    "images": {
      "large": "https://cdn.myanimelist.net/images/anime/1180/150596l.jpg",
      "medium": "https://cdn.myanimelist.net/images/anime/1180/150596.jpg"
    },
    "title": "New Panty & Stocking with Garterbelt",
    "title_english": "",
    "num_episodes": 0,
    "score": 8.06,
    "streams": null,
    "episode": "4",
    "karma": 620,
    "comments": 134,
    "week_id": 5,
    "studio": [
      "Trigger"
    ],
    "url": "https://www.reddit.com/r/anime/comments/1mdanax/new_panty_stocking_with_garterbelt_episode_4/",
    "mal_id": 52293,
    "current_rank": 16,
    "karma_change": -7,
    "rank_change": 2,
    "season": "summer"
  },
  {
    "images": {
      "large": "https://cdn.myanimelist.net/images/anime/1587/149982l.jpg",
      "medium": "https://cdn.myanimelist.net/images/anime/1587/149982.jpg"
    },
    "title": "Nukitashi the Animation",
    "title_english": "",
    "num_episodes": 11,
    "score": 7.34,
    "streams": null,
    "episode": "2",
    "karma": 571,
    "comments": 129,
    "week_id": 5,
    "studio": [
      "Passione"
    ],
    "url": "https://www.reddit.com/r/anime/comments/1m96kjx/nukitashi_the_animation_episode_2_discussion/",
    "mal_id": 57969,
    "current_rank": 17,
    "karma_change": -392,
    "rank_change": -5,
    "season": "summer"
  },
  {
    "images": {
      "large": "https://cdn.myanimelist.net/images/anime/1431/148742l.jpg",
      "medium": "https://cdn.myanimelist.net/images/anime/1431/148742.jpg"
    },
    "title": "Ruri no Houseki",
    "title_english": "Ruri Rocks",
    "num_episodes": 0,
    "score": 7.67,
    "streams": null,
    "episode": "4",
    "karma": 564,
    "comments": 139,
    "week_id": 5,
    "studio": [
      "Studio Bind"
    ],
    "url": "https://www.reddit.com/r/anime/comments/1mamfj2/ruri_no_houseki_ruri_rocks_episode_4_discussion/",
    "mal_id": 59791,
    "current_rank": 18,
    "karma_change": -38,
    "rank_change": 2,
    "season": "summer"
  },
  {
    "images": {
      "large": "https://cdn.myanimelist.net/images/anime/1244/138851l.jpg",
      "medium": "https://cdn.myanimelist.net/images/anime/1244/138851.jpg"
    },
    "num_episodes": 0,
    "score": null,
    "streams": {
      "name": "crunchyroll",
      "url": "https://www.crunchyroll.com/series/GRMG8ZQZR/one-piece",
      "logo": "https://1000logos.net/wp-content/uploads/2021/05/Crunchyroll-Logo-2018.png"
    },
    "title": "One Piece",
    "title_english": "One Piece",
    "episode": "1137",
    "karma": 554,
    "comments": 95,
    "week_id": 5,
    "studio": [
      "Toei Animation"
    ],
    "url": "https://www.reddit.com/r/anime/comments/1mapqip/one_piece_episode_1137_discussion/",
    "mal_id": 21,
    "current_rank": 19,
    "karma_change": 0,
    "rank_change": "returning",
    "season": "summer"
  },
  {
    "images": {
      "large": "https://cdn.myanimelist.net/images/anime/1782/150383l.webp",
      "medium": "https://cdn.myanimelist.net/images/anime/1782/150383.webp"
    },
    "title": "Isekai Mokushiroku Mynoghra: Hametsu no Bunmei de Hajimeru Sekai Seifuku",
    "title_english": "Apocalypse Bringer Mynoghra: World Conquest Starts with the Civilization of Ruin",
    "num_episodes": 0,
    "score": 7.04,
    "streams": null,
    "episode": "4",
    "karma": 517,
    "comments": 295,
    "week_id": 5,
    "studio": [
      "Maho Film"
    ],
    "url": "https://www.reddit.com/r/anime/comments/1mamfns/isekai_mokushiroku_mynoghra_hametsu_no_bunmei_de/",
    "mal_id": 59130,
    "current_rank": 20,
    "karma_change": 79,
    "rank_change": 2,
    "season": "summer"
  },
  {
    "images": {
      "large": "https://cdn.myanimelist.net/images/anime/1758/148719l.jpg",
      "medium": "https://cdn.myanimelist.net/images/anime/1758/148719.jpg"
    },
    "title": "Sakamoto Days Part 2",
    "title_english": "Sakamoto Days Part 2",
    "num_episodes": 0,
    "score": 7.9,
    "streams": null,
    "episode": "4",
    "karma": 481,
    "comments": 106,
    "week_id": 5,
    "studio": [
      "TMS Entertainment"
    ],
    "url": "https://www.reddit.com/r/anime/comments/1mbjfqy/sakamoto_days_part_2_episode_4_discussion/",
    "mal_id": 60285,
    "current_rank": 21,
    "karma_change": 72,
    "rank_change": 3,
    "season": "summer"
  },
  {
    "images": {
      "large": "https://cdn.myanimelist.net/images/anime/1039/150572l.jpg",
      "medium": "https://cdn.myanimelist.net/images/anime/1039/150572.jpg"
    },
    "title": "Food Court de, Mata Ashita.",
    "title_english": "See You Tomorrow at the Food Court",
    "num_episodes": 6,
    "score": 6.94,
    "streams": null,
    "episode": "4",
    "karma": 479,
    "comments": 150,
    "week_id": 5,
    "studio": [
      "Atelier Pontdarc"
    ],
    "url": "https://www.reddit.com/r/anime/comments/1mbfm76/food_court_de_mata_ashita_see_you_tomorrow_at_the/",
    "mal_id": 60508,
    "current_rank": 22,
    "karma_change": -17,
    "rank_change": -1,
    "season": "summer"
  },
  {
    "images": {
      "large": "https://cdn.myanimelist.net/images/anime/1359/150664l.jpg",
      "medium": "https://cdn.myanimelist.net/images/anime/1359/150664.jpg"
    },
    "title": "Mikadono Sanshimai wa Angai, Choroi.",
    "title_english": "Dealing with Mikadono Sisters Is a Breeze",
    "num_episodes": 0,
    "score": 7.58,
    "streams": null,
    "episode": "5",
    "karma": 427,
    "comments": 162,
    "week_id": 5,
    "studio": [
      "P.A. Works"
    ],
    "url": "https://www.reddit.com/r/anime/comments/1mdc2kd/mikadono_sanshimai_wa_angai_choroi_dealing_with/",
    "mal_id": 59207,
    "current_rank": 23,
    "karma_change": 2,
    "rank_change": 0,
    "season": "summer"
  },
  {
    "images": {
      "large": "https://cdn.myanimelist.net/images/anime/1672/148848l.jpg",
      "medium": "https://cdn.myanimelist.net/images/anime/1672/148848.jpg"
    },
    "title": "Bad Girl",
    "title_english": "Bad Girl",
    "num_episodes": 0,
    "score": 6.85,
    "streams": null,
    "episode": "4",
    "karma": 328,
    "comments": 65,
    "week_id": 5,
    "studio": [
      "Bridge"
    ],
    "url": "https://www.reddit.com/r/anime/comments/1m9wdii/bad_girl_episode_4_discussion/",
    "mal_id": 59161,
    "current_rank": 24,
    "karma_change": -31,
    "rank_change": 1,
    "season": "summer"
  },
  {
    "images": {
      "large": "https://cdn.myanimelist.net/images/anime/1691/148602l.jpg",
      "medium": "https://cdn.myanimelist.net/images/anime/1691/148602.jpg"
    },
    "num_episodes": 0,
    "score": 7.35,
    "streams": {
      "name": "crunchyroll",
      "url": "https://www.crunchyroll.com/series/G0XHWM17X/summer-pockets",
      "logo": "https://1000logos.net/wp-content/uploads/2021/05/Crunchyroll-Logo-2018.png"
    },
    "title": "Summer Pockets",
    "title_english": "Summer Pockets",
    "episode": "17",
    "karma": 312,
    "comments": 97,
    "week_id": 5,
    "studio": [
      "feel."
    ],
    "url": "https://www.reddit.com/r/anime/comments/1mbimtc/summer_pockets_episode_17_discussion/",
    "mal_id": 50694,
    "current_rank": 25,
    "karma_change": 35,
    "rank_change": 4,
    "season": "summer"
  },
  {
    "images": {
      "large": "https://cdn.myanimelist.net/images/anime/1423/142919l.jpg",
      "medium": "https://cdn.myanimelist.net/images/anime/1423/142919.jpg"
    },
    "num_episodes": 0,
    "score": 7.49,
    "streams": {
      "name": "hidive",
      "url": "https://www.hidive.com/season/30168",
      "logo": "https://static.wikia.nocookie.net/enanimanga/images/4/47/HIDIVE_logo.png"
    },
    "title": "Kijin Gentoushou",
    "title_english": "Sword of the Demon Hunter: Kijin Gentosho",
    "episode": "16",
    "karma": 302,
    "comments": 112,
    "week_id": 5,
    "studio": [
      "Yokohama Animation Laboratory"
    ],
    "url": "https://www.reddit.com/r/anime/comments/1mbin16/kijin_gentoushou_sword_of_the_demon_hunter_kijin/",
    "mal_id": 49778,
    "current_rank": 26,
    "karma_change": 49,
    "rank_change": 6,
    "season": "summer"
  },
  {
    "images": {
      "large": "https://cdn.myanimelist.net/images/anime/1323/149460l.jpg",
      "medium": "https://cdn.myanimelist.net/images/anime/1323/149460.jpg"
    },
    "title": "Mattaku Saikin no Tantei to Kitara",
    "title_english": "Detectives These Days Are Crazy!",
    "num_episodes": 12,
    "score": 7.13,
    "streams": null,
    "episode": "5",
    "karma": 299,
    "comments": 93,
    "week_id": 5,
    "studio": [
      "LIDENFILMS"
    ],
    "url": "https://www.reddit.com/r/anime/comments/1mcd34c/mattaku_saikin_no_tantei_to_kitara_detectives/",
    "mal_id": 59632,
    "current_rank": 27,
    "karma_change": -1,
    "rank_change": 0,
    "season": "summer"
  },
  {
    "images": {
      "large": "https://cdn.myanimelist.net/images/anime/1329/150512l.jpg",
      "medium": "https://cdn.myanimelist.net/images/anime/1329/150512.jpg"
    },
    "title": "Ame to Kimi to",
    "title_english": "With You and the Rain",
    "num_episodes": 0,
    "score": 7.46,
    "streams": null,
    "episode": "4",
    "karma": 261,
    "comments": 88,
    "week_id": 5,
    "studio": [
      "Lesprit"
    ],
    "url": "https://www.reddit.com/r/anime/comments/1m9zxa4/ame_to_kimi_to_with_you_and_the_rain_episode_4/",
    "mal_id": 59619,
    "current_rank": 28,
    "karma_change": -33,
    "rank_change": 0,
    "season": "summer"
  },
  {
    "images": {
      "large": "https://cdn.myanimelist.net/images/anime/1674/147871l.jpg",
      "medium": "https://cdn.myanimelist.net/images/anime/1674/147871.jpg"
    },
    "num_episodes": 24,
    "score": 7.8,
    "streams": {
      "name": "crunchyroll",
      "url": "https://www.crunchyroll.com/series/G8DHV78XM/anne-shirley",
      "logo": "https://1000logos.net/wp-content/uploads/2021/05/Crunchyroll-Logo-2018.png"
    },
    "title": "Anne Shirley",
    "title_english": "Anne Shirley",
    "episode": "17",
    "karma": 260,
    "comments": 51,
    "week_id": 5,
    "studio": [
      "The Answer Studio"
    ],
    "url": "https://www.reddit.com/r/anime/comments/1m9t65v/anne_shirley_episode_17_discussion/",
    "mal_id": 60334,
    "current_rank": 29,
    "karma_change": -10,
    "rank_change": 2,
    "season": "summer"
  },
  {
    "images": {
      "large": "https://cdn.myanimelist.net/images/anime/1297/150516l.jpg",
      "medium": "https://cdn.myanimelist.net/images/anime/1297/150516.jpg"
    },
    "title": "Jidou Hanbaiki ni Umarekawatta Ore wa Meikyuu wo Samayou 2nd Season",
    "title_english": "Reborn as a Vending Machine, I Now Wander the Dungeon Season 2",
    "num_episodes": 0,
    "score": 6.64,
    "streams": null,
    "episode": "5",
    "karma": 249,
    "comments": 60,
    "week_id": 5,
    "studio": [
      "Studio Gokumi",
      "AXsiZ"
    ],
    "url": "https://www.reddit.com/r/anime/comments/1md85ad/jidou_hanbaiki_ni_umarekawatta_ore_wa_meikyuu_wo/",
    "mal_id": 56700,
    "current_rank": 30,
    "karma_change": -24,
    "rank_change": 0,
    "season": "summer"
  },
  {
    "images": {
      "large": "https://cdn.myanimelist.net/images/anime/1790/149462l.jpg",
      "medium": "https://cdn.myanimelist.net/images/anime/1790/149462.jpg"
    },
    "title": "Arknights: Rise from Ember",
    "title_english": "Arknights: Rise from Ember",
    "num_episodes": 10,
    "score": 7.72,
    "streams": null,
    "episode": "4",
    "karma": 241,
    "comments": 85,
    "week_id": 5,
    "studio": [
      "Yostar Pictures"
    ],
    "url": "https://www.reddit.com/r/anime/comments/1m91hy1/arknights_homura_shomei_arknights_rise_from_ember/",
    "mal_id": 58749,
    "current_rank": 31,
    "karma_change": 43,
    "rank_change": 6,
    "season": "summer"
  },
  {
    "images": {
      "large": "https://cdn.myanimelist.net/images/anime/1977/150952l.jpg",
      "medium": "https://cdn.myanimelist.net/images/anime/1977/150952.jpg"
    },
    "title": "Turkey!",
    "title_english": "Turkey! Time to Strike",
    "num_episodes": 0,
    "score": 6.33,
    "streams": null,
    "episode": "4",
    "karma": 235,
    "comments": 101,
    "week_id": 5,
    "studio": [
      "Bakken Record"
    ],
    "url": "https://www.reddit.com/r/anime/comments/1mcjjcb/turkey_episode_4_discussion/",
    "mal_id": 54028,
    "current_rank": 32,
    "karma_change": -66,
    "rank_change": -6,
    "season": "summer"
  },
  {
    "images": {
      "large": "https://cdn.myanimelist.net/images/anime/1638/150592l.jpg",
      "medium": "https://cdn.myanimelist.net/images/anime/1638/150592.jpg"
    },
    "title": "Tate no Yuusha no Nariagari Season 4",
    "title_english": "The Rising of the Shield Hero Season 4",
    "num_episodes": 12,
    "score": 7.39,
    "streams": null,
    "episode": "4",
    "karma": 233,
    "comments": 167,
    "week_id": 5,
    "studio": [
      "Kinema Citrus"
    ],
    "url": "https://www.reddit.com/r/anime/comments/1md4ph6/tate_no_yuusha_no_nariagari_season_4_the_rising/",
    "mal_id": 57907,
    "current_rank": 33,
    "karma_change": -6,
    "rank_change": 0,
    "season": "summer"
  },
  {
    "images": {
      "large": "https://cdn.myanimelist.net/images/anime/1454/150515l.jpg",
      "medium": "https://cdn.myanimelist.net/images/anime/1454/150515.jpg"
    },
    "title": "Busamen Gachi Fighter",
    "title_english": "Uglymug, Epicfighter",
    "num_episodes": 0,
    "score": 6.55,
    "streams": null,
    "episode": "4",
    "karma": 208,
    "comments": 119,
    "week_id": 5,
    "studio": [
      "White Fox"
    ],
    "url": "https://www.reddit.com/r/anime/comments/1mantxl/busamen_gachi_fighter_uglymug_epicfighter_episode/",
    "mal_id": 60316,
    "current_rank": 34,
    "karma_change": -9,
    "rank_change": 0,
    "season": "summer"
  },
  {
    "images": {
      "large": "https://cdn.myanimelist.net/images/anime/1777/150455l.jpg",
      "medium": "https://cdn.myanimelist.net/images/anime/1777/150455.jpg"
    },
    "title": "Kizetsu Yuusha to Ansatsu Hime",
    "title_english": "The Shy Hero and the Assassin Princesses",
    "num_episodes": 0,
    "score": 6.42,
    "streams": null,
    "episode": "4",
    "karma": 199,
    "comments": 57,
    "week_id": 5,
    "studio": [
      "Connect"
    ],
    "url": "https://www.reddit.com/r/anime/comments/1m9u83w/kizetsu_yuusha_to_ansatsu_hime_the_shy_hero_and/",
    "mal_id": 60951,
    "current_rank": 35,
    "karma_change": -9,
    "rank_change": 0,
    "season": "summer"
  },
  {
    "images": {
      "large": "https://cdn.myanimelist.net/images/anime/1943/149719l.jpg",
      "medium": "https://cdn.myanimelist.net/images/anime/1943/149719.jpg"
    },
    "title": "Game Center Shoujo to Ibunka Kouryuu",
    "title_english": "Cultural Exchange With a Game Centre Girl",
    "num_episodes": 0,
    "score": 6.93,
    "streams": null,
    "episode": "4",
    "karma": 190,
    "comments": 50,
    "week_id": 5,
    "studio": [
      "Nomad"
    ],
    "url": "https://www.reddit.com/r/anime/comments/1mao3xe/game_center_shoujo_to_ibunka_kouryuu_cultural/",
    "mal_id": 59689,
    "current_rank": 36,
    "karma_change": -12,
    "rank_change": 0,
    "season": "summer"
  },
  {
    "images": {
      "large": "https://cdn.myanimelist.net/images/anime/1502/150545l.jpg",
      "medium": "https://cdn.myanimelist.net/images/anime/1502/150545.jpg"
    },
    "title": "Watari-kun no xx ga Houkai Sunzen",
    "title_english": "Watari-kun's ****** Is about to Collapse",
    "num_episodes": 0,
    "score": 6.43,
    "streams": null,
    "episode": "4",
    "karma": 150,
    "comments": 50,
    "week_id": 5,
    "studio": [
      "Staple Entertainment"
    ],
    "url": "https://www.reddit.com/r/anime/comments/1m93k7x/watarikun_no_xx_ga_houkai_sunzen_watarikuns_is/",
    "mal_id": 56693,
    "current_rank": 37,
    "karma_change": -20,
    "rank_change": 4,
    "season": "summer"
  },
  {
    "images": {
      "large": "https://cdn.myanimelist.net/images/anime/1518/149900l.jpg",
      "medium": "https://cdn.myanimelist.net/images/anime/1518/149900.jpg"
    },
    "title": "Zutaboro Reijou wa Ane no Moto Konyakusha ni Dekiai sareru",
    "title_english": "Betrothed to My Sister's Ex",
    "num_episodes": 0,
    "score": 7.21,
    "streams": null,
    "episode": "4",
    "karma": 142,
    "comments": 66,
    "week_id": 5,
    "studio": [
      "LandQ studios"
    ],
    "url": "https://www.reddit.com/r/anime/comments/1m95gyj/zutaboro_reijou_wa_ane_no_moto_konyakusha_ni/",
    "mal_id": 59421,
    "current_rank": 38,
    "karma_change": -9,
    "rank_change": 6,
    "season": "summer"
  },
  {
    "images": {
      "large": "https://cdn.myanimelist.net/images/anime/1551/150517l.jpg",
      "medium": "https://cdn.myanimelist.net/images/anime/1551/150517.jpg"
    },
    "title": "Kakkou no Iinazuke Season 2",
    "title_english": "A Couple of Cuckoos Season 2",
    "num_episodes": 0,
    "score": 7.06,
    "streams": null,
    "episode": "4",
    "karma": 138,
    "comments": 36,
    "week_id": 5,
    "studio": [
      "Okuruto Noboru"
    ],
    "url": "https://www.reddit.com/r/anime/comments/1mccbpz/kakkou_no_iinazuke_season_2_a_couple_of_cuckoos/",
    "mal_id": 59402,
    "current_rank": 39,
    "karma_change": 22,
    "rank_change": 10,
    "season": "summer"
  },
  {
    "images": {
      "large": "https://cdn.myanimelist.net/images/anime/1474/150666l.jpg",
      "medium": "https://cdn.myanimelist.net/images/anime/1474/150666.jpg"
    },
    "title": "Tougen Anki",
    "title_english": "Tougen Anki",
    "num_episodes": 0,
    "score": 7.06,
    "streams": null,
    "episode": "3",
    "karma": 137,
    "comments": 76,
    "week_id": 5,
    "studio": [
      "Studio Hibari"
    ],
    "url": "https://www.reddit.com/r/anime/comments/1m92afw/tougen_anki_episode_3_discussion/",
    "mal_id": 58811,
    "current_rank": 40,
    "karma_change": -15,
    "rank_change": 3,
    "season": "summer"
  },
  {
    "images": {
      "large": "https://cdn.myanimelist.net/images/anime/1072/149889l.jpg",
      "medium": "https://cdn.myanimelist.net/images/anime/1072/149889.jpg"
    },
    "title": "Yuusha Party wo Tsuihou sareta Shiromadoushi, S-Rank Boukensha ni Hirowareru: Kono Shiromadoushi ga Kikakugai Sugiru",
    "title_english": "Scooped Up by an S-Ranked Adventurer",
    "num_episodes": 0,
    "score": 6.54,
    "streams": null,
    "episode": "4",
    "karma": 132,
    "comments": 108,
    "week_id": 5,
    "studio": [
      "Felix Film"
    ],
    "url": "https://www.reddit.com/r/anime/comments/1m9vnaq/yuusha_party_wo_tsuihou_sareta_shiromadoushi/",
    "mal_id": 59424,
    "current_rank": 41,
    "karma_change": -14,
    "rank_change": 4,
    "season": "summer"
  },
  {
    "images": {
      "large": "https://cdn.myanimelist.net/images/anime/1878/146291l.jpg",
      "medium": "https://cdn.myanimelist.net/images/anime/1878/146291.jpg"
    },
    "num_episodes": 12,
    "score": 7.9,
    "streams": {
      "name": "crunchyroll",
      "url": "https://www.crunchyroll.com/toilet-bound-hanako-kunhttps://www.hulu.com/series/toilet-bound-hanako-kun-87b3d986-cbae-47ce-9076-0fe61fce06e3",
      "logo": "https://1000logos.net/wp-content/uploads/2021/05/Crunchyroll-Logo-2018.png"
    },
    "title": "Jibaku Shounen Hanako-kun 2",
    "title_english": "Toilet-Bound Hanako-kun Season 2",
    "episode": "16",
    "karma": 126,
    "comments": 26,
    "week_id": 5,
    "studio": [
      "Lerche"
    ],
    "url": "https://www.reddit.com/r/anime/comments/1mahpfv/jibaku_shounen_hanakokun_season_2_toiletbound/",
    "mal_id": 53924,
    "current_rank": 42,
    "karma_change": -15,
    "rank_change": 4,
    "season": "summer"
  },
  {
    "images": {
      "large": "https://cdn.myanimelist.net/images/anime/1071/150808l.jpg",
      "medium": "https://cdn.myanimelist.net/images/anime/1071/150808.jpg"
    },
    "title": "Kanojo, Okarishimasu 4th Season",
    "title_english": "Rent-a-Girlfriend Season 4",
    "num_episodes": 0,
    "score": 6.22,
    "streams": null,
    "episode": "5",
    "karma": 120,
    "comments": 92,
    "week_id": 5,
    "studio": [
      "TMS Entertainment"
    ],
    "url": "https://www.reddit.com/r/anime/comments/1mcbipt/kanojo_okarishimasu_season_4_rentagirlfriend/",
    "mal_id": 59277,
    "current_rank": 43,
    "karma_change": 16,
    "rank_change": 9,
    "season": "summer"
  },
  {
    "images": {
      "large": "https://cdn.myanimelist.net/images/anime/1961/149183l.jpg",
      "medium": "https://cdn.myanimelist.net/images/anime/1961/149183.jpg"
    },
    "title": "Hitozuma no Kuchibiru wa Kan Chuuhai no Aji ga Shite",
    "title_english": "Chuhai Lips",
    "num_episodes": 8,
    "score": 5.84,
    "streams": null,
    "episode": "5",
    "karma": 118,
    "comments": 28,
    "week_id": 5,
    "studio": [
      "Raiose"
    ],
    "url": "https://www.reddit.com/r/anime/comments/1mcffz0/hitozuma_no_kuchibiru_wa_kan_chuuhai_no_aji_ga/",
    "mal_id": 61023,
    "current_rank": 44,
    "karma_change": 13,
    "rank_change": 7,
    "season": "summer"
  },
  {
    "images": {
      "large": "https://cdn.myanimelist.net/images/anime/1942/148242l.jpg",
      "medium": "https://cdn.myanimelist.net/images/anime/1942/148242.jpg"
    },
    "num_episodes": 0,
    "score": 7.4,
    "streams": {
      "name": "netflix",
      "url": "https://www.netflix.com/title/82030192"
    },
    "title": "Shin Samurai-den Yaiba",
    "title_english": "Yaiba: Samurai Legend",
    "episode": "16",
    "karma": 105,
    "comments": 36,
    "week_id": 5,
    "studio": [
      "Wit Studio"
    ],
    "url": "https://www.reddit.com/r/anime/comments/1m9p8c2/shin_samuraiden_yaiba_yaiba_samurai_legend/",
    "mal_id": 58812,
    "current_rank": 45,
    "karma_change": 0,
    "rank_change": "returning",
    "season": "summer"
  },
  {
    "images": {
      "large": "https://cdn.myanimelist.net/images/anime/1411/150445l.jpg",
      "medium": "https://cdn.myanimelist.net/images/anime/1411/150445.jpg"
    },
    "title": "Nyaight of the Living Cat",
    "title_english": "Nyaight of the Living Cat",
    "num_episodes": 0,
    "score": 6.41,
    "streams": null,
    "episode": "4",
    "karma": 105,
    "comments": 27,
    "week_id": 5,
    "studio": [
      "OLM"
    ],
    "url": "https://www.reddit.com/r/anime/comments/1maneev/nyaight_of_the_living_cat_episode_4_discussion/",
    "mal_id": 58197,
    "current_rank": 46,
    "karma_change": -22,
    "rank_change": 1,
    "season": "summer"
  },
  {
    "images": {
      "large": "https://cdn.myanimelist.net/images/anime/1672/148193l.jpg",
      "medium": "https://cdn.myanimelist.net/images/anime/1672/148193.jpg"
    },
    "title": "Busu ni Hanataba wo.",
    "title_english": "",
    "num_episodes": 0,
    "score": 6.68,
    "streams": null,
    "episode": "4",
    "karma": 103,
    "comments": 31,
    "week_id": 5,
    "studio": [
      "SILVER LINK."
    ],
    "url": "https://www.reddit.com/r/anime/comments/1m90vgq/busu_ni_hanataba_wo_april_showers_bring_may/",
    "mal_id": 53512,
    "current_rank": 47,
    "karma_change": 9,
    "rank_change": 6,
    "season": "summer"
  },
  {
    "images": {
      "large": "https://cdn.myanimelist.net/images/anime/1900/150443l.jpg",
      "medium": "https://cdn.myanimelist.net/images/anime/1900/150443.jpg"
    },
    "title": "Hotel Inhumans",
    "title_english": "Hotel Inhumans",
    "num_episodes": 0,
    "score": 6.6,
    "streams": null,
    "episode": "4",
    "karma": 93,
    "comments": 44,
    "week_id": 5,
    "studio": [
      "Bridge"
    ],
    "url": "https://www.reddit.com/r/anime/comments/1maqswk/hotel_inhumans_episode_4_discussion/",
    "mal_id": 60260,
    "current_rank": 48,
    "karma_change": -20,
    "rank_change": 2,
    "season": "summer"
  },
  {
    "images": {
      "large": "https://cdn.myanimelist.net/images/anime/1933/150503l.jpg",
      "medium": "https://cdn.myanimelist.net/images/anime/1933/150503.jpg"
    },
    "title": "Onmyou Kaiten Re:Birth",
    "title_english": "Onmyo Kaiten Re:Birth Verse",
    "num_episodes": 0,
    "score": 6.53,
    "streams": null,
    "episode": "5",
    "karma": 87,
    "comments": 73,
    "week_id": 5,
    "studio": [
      "David Production"
    ],
    "url": "https://www.reddit.com/r/anime/comments/1mdcpxv/onmyou_kaiten_rebirth_onmyo_kaiten_rebirth_verse/",
    "mal_id": 61150,
    "current_rank": 49,
    "karma_change": -5,
    "rank_change": 5,
    "season": "summer"
  },
  {
    "images": {
      "large": "https://cdn.myanimelist.net/images/anime/1845/150343l.jpg",
      "medium": "https://cdn.myanimelist.net/images/anime/1845/150343.jpg"
    },
    "title": "Necronomico no Cosmic Horror Show",
    "title_english": "Necronomico and the Cosmic Horror Show",
    "num_episodes": 0,
    "score": 5.5,
    "streams": null,
    "episode": "5",
    "karma": 78,
    "comments": 70,
    "week_id": 5,
    "studio": [
      "Studio Gokumi"
    ],
    "url": "https://www.reddit.com/r/anime/comments/1mce652/necronomico_no_cosmic_horror_show_necronomico_and/",
    "mal_id": 60505,
    "current_rank": 50,
    "karma_change": 2,
    "rank_change": 5,
    "season": "summer"
  },
  {
    "images": {
      "large": "https://cdn.myanimelist.net/images/anime/1154/149311l.jpg",
      "medium": "https://cdn.myanimelist.net/images/anime/1154/149311.jpg"
    },
    "title": "Dekin no Mogura",
    "title_english": "Dekin no Mogura: The Earthbound Mole",
    "num_episodes": 0,
    "score": 6.19,
    "streams": null,
    "episode": "4",
    "karma": 60,
    "comments": 17,
    "week_id": 5,
    "studio": [
      "Brain's Base"
    ],
    "url": "https://www.reddit.com/r/anime/comments/1mam1gx/dekin_no_mogura_dekin_no_mogura_the_earthbound/",
    "mal_id": 60315,
    "current_rank": 51,
    "karma_change": -15,
    "rank_change": 5,
    "season": "summer"
  },
  {
    "images": {
      "large": "https://cdn.myanimelist.net/images/anime/1415/150405l.jpg",
      "medium": "https://cdn.myanimelist.net/images/anime/1415/150405.jpg"
    },
    "title": "Puniru wa Kawaii Slime 2nd Season",
    "title_english": "Puniru is a Kawaii Slime Season 2",
    "num_episodes": 0,
    "score": 6.96,
    "streams": null,
    "episode": "4",
    "karma": 58,
    "comments": 24,
    "week_id": 5,
    "studio": [
      "TOHO animation STUDIO"
    ],
    "url": "https://www.reddit.com/r/anime/comments/1mahpfj/puniru_wa_kawaii_slime_season_2_puniru_is_a/",
    "mal_id": 60603,
    "current_rank": 52,
    "karma_change": -2,
    "rank_change": 6,
    "season": "summer"
  },
  {
    "images": {
      "large": "https://cdn.myanimelist.net/images/anime/1104/150590l.jpg",
      "medium": "https://cdn.myanimelist.net/images/anime/1104/150590.jpg"
    },
    "title": "Fermat no Ryouri",
    "title_english": "",
    "num_episodes": 0,
    "score": 6.69,
    "streams": null,
    "episode": "4",
    "karma": 40,
    "comments": 22,
    "week_id": 5,
    "studio": [
      "domerica"
    ],
    "url": "https://www.reddit.com/r/anime/comments/1m9vhx7/fermat_no_ryouri_fermat_kitchen_episode_4/",
    "mal_id": 60697,
    "current_rank": 53,
    "karma_change": -3,
    "rank_change": 7,
    "season": "summer"
  },
  {
    "images": {
      "large": "https://cdn.myanimelist.net/images/anime/1979/148096l.jpg",
      "medium": "https://cdn.myanimelist.net/images/anime/1979/148096.jpg"
    },
    "num_episodes": 0,
    "score": 6.24,
    "streams": null,
    "title": "Uchuujin MuuMuu",
    "title_english": "Uchuujin MuuMuu",
    "episode": "17",
    "karma": 26,
    "comments": 10,
    "week_id": 5,
    "studio": [
      "OLM"
    ],
    "url": "https://www.reddit.com/r/anime/comments/1mdbagg/uchuujin_muumuu_me_and_the_alien_muumuu_episode/",
    "mal_id": 60401,
    "current_rank": 54,
    "karma_change": -5,
    "rank_change": 9,
    "season": "summer"
  },
  {
    "images": {
      "large": "https://cdn.myanimelist.net/images/anime/1866/150935l.jpg",
      "medium": "https://cdn.myanimelist.net/images/anime/1866/150935.jpg"
    },
    "title": "Utagoe wa Mille-Feuille",
    "title_english": "Harmony of Mille-Feuille",
    "num_episodes": 10,
    "score": 6.13,
    "streams": null,
    "episode": "2",
    "karma": 23,
    "comments": 13,
    "week_id": 5,
    "studio": [
      "Jumondou"
    ],
    "url": "https://www.reddit.com/r/anime/comments/1m9n94e/utagoe_wa_millefeuille_harmony_of_millefeuille/",
    "mal_id": 55689,
    "current_rank": 55,
    "karma_change": -16,
    "rank_change": 7,
    "season": "summer"
  },
  {
    "images": {
      "large": "https://cdn.myanimelist.net/images/anime/1277/147358l.jpg",
      "medium": "https://cdn.myanimelist.net/images/anime/1277/147358.jpg"
    },
    "num_episodes": 49,
    "score": 7.46,
    "streams": {},
    "title": "Kimi to Idol Precure\u266a",
    "title_english": "You and Idol Precure\u266a",
    "episode": "25",
    "karma": 19,
    "comments": 13,
    "week_id": 5,
    "studio": [
      "Toei Animation"
    ],
    "url": "https://www.reddit.com/r/anime/comments/1maa0kk/kimi_to_idol_precure_you_and_idol_precure_episode/",
    "mal_id": 60407,
    "current_rank": 56,
    "karma_change": 2,
    "rank_change": 8,
    "season": "summer"
  },
  {
    "images": {
      "large": "https://cdn.myanimelist.net/images/anime/1018/150416l.jpg",
      "medium": "https://cdn.myanimelist.net/images/anime/1018/150416.jpg"
    },
    "title": "Osomatsu-san 4th Season",
    "title_english": "Mr. Osomatsu 4th Season",
    "num_episodes": 0,
    "score": 6.72,
    "streams": null,
    "episode": "4",
    "karma": 13,
    "comments": 9,
    "week_id": 5,
    "studio": [
      "Pierrot Films"
    ],
    "url": "https://www.reddit.com/r/anime/comments/1mch2tc/osomatsusan_season_4_mr_osomatsu_season_4_episode/",
    "mal_id": 58996,
    "current_rank": 57,
    "karma_change": 0,
    "rank_change": 10,
    "season": "summer"
  },
  {
    "images": {
      "large": "https://cdn.myanimelist.net/images/anime/7/75199l.jpg",
      "medium": "https://cdn.myanimelist.net/images/anime/7/75199.jpg"
    },
    "num_episodes": 0,
    "score": null,
    "streams": null,
    "title": "Meitantei Conan",
    "title_english": "Case Closed",
    "episode": "1169",
    "karma": 10,
    "comments": 3,
    "week_id": 5,
    "studio": [
      "TMS Entertainment"
    ],
    "url": "https://www.reddit.com/r/anime/comments/1m9r1rp/meitantei_conan_case_closed_episode_1169/",
    "mal_id": 235,
    "current_rank": 58,
    "karma_change": 8,
    "rank_change": 18,
    "season": "summer"
  },
  {
    "images": {
      "large": "https://cdn.myanimelist.net/images/anime/1546/145782l.jpg",
      "medium": "https://cdn.myanimelist.net/images/anime/1546/145782.jpg"
    },
    "title": "Kizu darake Seijo yori Houfuku wo Komete",
    "title_english": "",
    "num_episodes": 0,
    "score": 5.56,
    "streams": null,
    "episode": "4",
    "karma": 9,
    "comments": 8,
    "week_id": 5,
    "studio": [
      "Imagica Infos",
      "Imageworks Studio"
    ],
    "url": "https://www.reddit.com/r/anime/comments/1mdc8py/kizu_darake_seijo_yori_houfuku_wo_komete_with/",
    "mal_id": 59961,
    "current_rank": 59,
    "karma_change": -4,
    "rank_change": 9,
    "season": "summer"
  },
  {
    "images": {
      "large": "https://cdn.myanimelist.net/images/anime/1241/144618l.jpg",
      "medium": "https://cdn.myanimelist.net/images/anime/1241/144618.jpg"
    },
    "title": "Yoru wa Neko to Issho Season 3",
    "title_english": "Yoru wa Neko to Issho Season 3",
    "num_episodes": 0,
    "score": 6.68,
    "streams": null,
    "episode": "95",
    "karma": 9,
    "comments": 3,
    "week_id": 5,
    "studio": [
      "Studio PuYUKAI"
    ],
    "url": "https://www.reddit.com/r/anime/comments/1md3sfo/yoru_wa_neko_to_issho_season_3_nights_with_a_cat/",
    "mal_id": 58199,
    "current_rank": 60,
    "karma_change": -5,
    "rank_change": 6,
    "season": "summer"
  },
  {
    "images": {
      "large": "https://cdn.myanimelist.net/images/anime/1278/149789l.jpg",
      "medium": "https://cdn.myanimelist.net/images/anime/1278/149789.jpg"
    },
    "title": "9: Ruler's Crown",
    "title_english": "",
    "num_episodes": 13,
    "score": 5.93,
    "streams": null,
    "episode": "5",
    "karma": 7,
    "comments": 19,
    "week_id": 5,
    "studio": [
      "PRA"
    ],
    "url": "https://www.reddit.com/r/anime/comments/1ma4pfz/9_rulers_crown_episode_5_discussion/",
    "mal_id": 58957,
    "current_rank": 61,
    "karma_change": -9,
    "rank_change": 4,
    "season": "summer"
  },
  {
    "images": {
      "large": "https://cdn.myanimelist.net/images/anime/1878/150315l.jpg",
      "medium": "https://cdn.myanimelist.net/images/anime/1878/150315.jpg"
    },
    "title": "Cardfight!! Vanguard: Divinez Deluxe Kesshou-hen",
    "title_english": "",
    "num_episodes": 0,
    "score": null,
    "streams": null,
    "episode": "4",
    "karma": 7,
    "comments": 3,
    "week_id": 5,
    "studio": [],
    "url": "https://www.reddit.com/r/anime/comments/1m9do6u/cardfight_vanguard_divinez_deluxe_kesshouhen/",
    "mal_id": 54145,
    "current_rank": 62,
    "karma_change": 1,
    "rank_change": 10,
    "season": "summer"
  },
  {
    "images": {
      "large": "https://cdn.myanimelist.net/images/anime/1533/146981l.jpg",
      "medium": "https://cdn.myanimelist.net/images/anime/1533/146981.jpg"
    },
    "title": "Koupen-chan",
    "title_english": "Koupen-chan",
    "num_episodes": 0,
    "score": 6.63,
    "streams": null,
    "episode": "17",
    "karma": 4,
    "comments": 3,
    "week_id": 5,
    "studio": [
      "Lesprit"
    ],
    "url": "https://www.reddit.com/r/anime/comments/1maxecw/koupen_chan_episode_17_discussion/",
    "mal_id": 60534,
    "current_rank": 63,
    "karma_change": -4,
    "rank_change": 7,
    "season": "summer"
  },
  {
    "images": {
      "large": "https://cdn.myanimelist.net/images/anime/1975/150436l.jpg",
      "medium": "https://cdn.myanimelist.net/images/anime/1975/150436.jpg"
    },
    "title": "Yami Shibai 15",
    "title_english": "Theatre of Darkness: Yamishibai 15",
    "num_episodes": 0,
    "score": 5.97,
    "streams": null,
    "episode": "3",
    "karma": 0,
    "comments": 2,
    "week_id": 5,
    "studio": [
      "ILCA"
    ],
    "url": "https://www.reddit.com/r/anime/comments/1mavpe3/yami_shibai_season_15_theatre_of_darkness/",
    "mal_id": 61793,
    "current_rank": 64,
    "karma_change": -4,
    "rank_change": 9,
    "season": "summer"
  },
  {
    "images": {
      "large": "https://cdn.myanimelist.net/images/anime/1394/145458l.jpg",
      "medium": "https://cdn.myanimelist.net/images/anime/1394/145458.jpg"
    },
    "num_episodes": 0,
    "score": 6.81,
    "streams": null,
    "title": "Beyblade X",
    "title_english": "Beyblade X",
    "episode": "89",
    "karma": 0,
    "comments": 1,
    "week_id": 5,
    "studio": [
      "OLM"
    ],
    "url": "https://www.reddit.com/r/anime/comments/1mckco9/beyblade_x_episode_89_discussion/",
    "mal_id": 56566,
    "current_rank": 65,
    "karma_change": 0,
    "rank_change": "returning",
    "season": "summer"
  }
]