[{"mal_id": 57554, "progression": [{"hour": 4.83, "karma": 58}, {"hour": 21.83, "karma": 136}, {"hour": 22.83, "karma": 142}, {"hour": 23.83, "karma": 140}, {"hour": 24.83, "karma": 142}, {"hour": 25.83, "karma": 145}, {"hour": 26.83, "karma": 143}, {"hour": 27.83, "karma": 143}, {"hour": 28.83, "karma": 147}, {"hour": 29.83, "karma": 147}, {"hour": 30.83, "karma": 145}, {"hour": 31.83, "karma": 146}, {"hour": 32.83, "karma": 144}, {"hour": 33.83, "karma": 146}, {"hour": 34.83, "karma": 149}, {"hour": 35.83, "karma": 147}, {"hour": 36.83, "karma": 149}, {"hour": 37.83, "karma": 146}, {"hour": 38.83, "karma": 148}, {"hour": 39.83, "karma": 146}, {"hour": 40.83, "karma": 147}, {"hour": 41.83, "karma": 145}, {"hour": 42.83, "karma": 148}, {"hour": 43.83, "karma": 147}]}, {"mal_id": 58259, "progression": [{"hour": 6.93, "karma": 18}, {"hour": 23.93, "karma": 25}, {"hour": 24.93, "karma": 27}, {"hour": 25.93, "karma": 29}, {"hour": 26.93, "karma": 27}, {"hour": 27.93, "karma": 28}, {"hour": 28.93, "karma": 25}, {"hour": 29.93, "karma": 29}, {"hour": 30.93, "karma": 29}, {"hour": 31.93, "karma": 27}, {"hour": 32.93, "karma": 27}, {"hour": 33.93, "karma": 29}, {"hour": 34.93, "karma": 29}, {"hour": 35.93, "karma": 30}, {"hour": 36.93, "karma": 33}, {"hour": 37.93, "karma": 34}, {"hour": 38.93, "karma": 29}, {"hour": 39.93, "karma": 33}, {"hour": 40.93, "karma": 29}, {"hour": 41.93, "karma": 28}, {"hour": 42.93, "karma": 31}, {"hour": 43.93, "karma": 27}, {"hour": 44.93, "karma": 29}, {"hour": 45.93, "karma": 29}]}, {"mal_id": 54769, "progression": [{"hour": 6.93, "karma": 2}, {"hour": 23.93, "karma": 6}, {"hour": 24.93, "karma": 7}, {"hour": 25.93, "karma": 8}, {"hour": 26.93, "karma": 7}, {"hour": 27.93, "karma": 7}, {"hour": 28.93, "karma": 9}, {"hour": 29.93, "karma": 9}, {"hour": 30.93, "karma": 9}, {"hour": 31.93, "karma": 11}, {"hour": 32.93, "karma": 8}, {"hour": 33.93, "karma": 9}, {"hour": 34.93, "karma": 10}, {"hour": 35.93, "karma": 10}, {"hour": 36.93, "karma": 10}, {"hour": 37.93, "karma": 8}, {"hour": 38.93, "karma": 10}, {"hour": 39.93, "karma": 8}, {"hour": 40.93, "karma": 9}, {"hour": 41.93, "karma": 11}, {"hour": 42.93, "karma": 8}, {"hour": 43.93, "karma": 11}, {"hour": 44.93, "karma": 12}, {"hour": 45.93, "karma": 11}]}, {"mal_id": 58739, "progression": [{"hour": 7.93, "karma": 49}, {"hour": 24.93, "karma": 89}, {"hour": 25.93, "karma": 85}, {"hour": 26.93, "karma": 85}, {"hour": 27.93, "karma": 89}, {"hour": 28.93, "karma": 87}, {"hour": 29.93, "karma": 89}, {"hour": 30.93, "karma": 87}, {"hour": 31.93, "karma": 88}, {"hour": 32.93, "karma": 87}, {"hour": 33.93, "karma": 92}, {"hour": 34.93, "karma": 91}, {"hour": 35.93, "karma": 91}, {"hour": 36.93, "karma": 92}, {"hour": 37.93, "karma": 88}, {"hour": 38.93, "karma": 93}, {"hour": 39.93, "karma": 88}, {"hour": 40.93, "karma": 87}, {"hour": 41.93, "karma": 91}, {"hour": 42.93, "karma": 90}, {"hour": 43.93, "karma": 87}, {"hour": 44.93, "karma": 89}, {"hour": 45.93, "karma": 85}, {"hour": 46.93, "karma": 86}]}, {"mal_id": 57719, "progression": [{"hour": 7.93, "karma": 280}, {"hour": 24.93, "karma": 470}, {"hour": 25.93, "karma": 473}, {"hour": 26.93, "karma": 480}, {"hour": 27.93, "karma": 481}, {"hour": 28.93, "karma": 490}, {"hour": 29.93, "karma": 489}, {"hour": 30.93, "karma": 488}, {"hour": 31.93, "karma": 492}, {"hour": 32.93, "karma": 494}, {"hour": 33.93, "karma": 495}, {"hour": 34.93, "karma": 495}, {"hour": 35.93, "karma": 497}, {"hour": 36.93, "karma": 505}, {"hour": 37.93, "karma": 503}, {"hour": 38.93, "karma": 505}, {"hour": 39.93, "karma": 501}, {"hour": 40.93, "karma": 508}, {"hour": 41.93, "karma": 509}, {"hour": 42.93, "karma": 513}, {"hour": 43.93, "karma": 510}, {"hour": 44.93, "karma": 514}, {"hour": 45.93, "karma": 509}, {"hour": 46.93, "karma": 514}]}, {"mal_id": 56653, "progression": [{"hour": 7.97, "karma": 304}, {"hour": 24.97, "karma": 453}, {"hour": 25.97, "karma": 453}, {"hour": 26.97, "karma": 451}, {"hour": 27.97, "karma": 457}, {"hour": 28.97, "karma": 462}, {"hour": 29.97, "karma": 463}, {"hour": 30.97, "karma": 461}, {"hour": 31.97, "karma": 465}, {"hour": 32.97, "karma": 465}, {"hour": 33.97, "karma": 464}, {"hour": 34.97, "karma": 462}, {"hour": 35.97, "karma": 468}, {"hour": 36.97, "karma": 467}, {"hour": 37.97, "karma": 466}, {"hour": 38.97, "karma": 473}, {"hour": 39.97, "karma": 465}, {"hour": 40.97, "karma": 473}, {"hour": 41.97, "karma": 477}, {"hour": 42.97, "karma": 470}, {"hour": 43.97, "karma": 479}, {"hour": 44.97, "karma": 478}, {"hour": 45.97, "karma": 478}, {"hour": 46.97, "karma": 475}]}, {"mal_id": 57592, "progression": [{"hour": 8.93, "karma": 421}, {"hour": 25.93, "karma": 702}, {"hour": 26.93, "karma": 711}, {"hour": 27.93, "karma": 715}, {"hour": 28.93, "karma": 730}, {"hour": 29.93, "karma": 726}, {"hour": 30.93, "karma": 737}, {"hour": 31.93, "karma": 747}, {"hour": 32.93, "karma": 749}, {"hour": 33.93, "karma": 745}, {"hour": 34.93, "karma": 745}, {"hour": 35.93, "karma": 752}, {"hour": 36.93, "karma": 759}, {"hour": 37.93, "karma": 756}, {"hour": 38.93, "karma": 763}, {"hour": 39.93, "karma": 762}, {"hour": 40.93, "karma": 761}, {"hour": 41.93, "karma": 767}, {"hour": 42.93, "karma": 761}, {"hour": 43.93, "karma": 764}, {"hour": 44.93, "karma": 767}, {"hour": 45.93, "karma": 766}, {"hour": 46.93, "karma": 777}, {"hour": 47.93, "karma": 770}]}, {"mal_id": 59144, "progression": [{"hour": 9.43, "karma": 29}, {"hour": 26.43, "karma": 50}, {"hour": 27.43, "karma": 44}, {"hour": 28.43, "karma": 49}, {"hour": 29.43, "karma": 49}, {"hour": 30.43, "karma": 48}, {"hour": 31.43, "karma": 47}, {"hour": 32.43, "karma": 52}, {"hour": 33.43, "karma": 52}, {"hour": 34.43, "karma": 49}, {"hour": 35.43, "karma": 47}, {"hour": 36.43, "karma": 55}, {"hour": 37.43, "karma": 52}, {"hour": 38.43, "karma": 55}, {"hour": 39.43, "karma": 53}, {"hour": 40.43, "karma": 50}, {"hour": 41.43, "karma": 54}, {"hour": 42.43, "karma": 50}, {"hour": 43.43, "karma": 56}, {"hour": 44.43, "karma": 54}, {"hour": 45.43, "karma": 55}, {"hour": 46.43, "karma": 53}, {"hour": 47.43, "karma": 56}]}, {"mal_id": 59561, "progression": [{"hour": 10.47, "karma": 109}, {"hour": 27.47, "karma": 167}, {"hour": 28.47, "karma": 168}, {"hour": 29.47, "karma": 172}, {"hour": 30.47, "karma": 168}, {"hour": 31.47, "karma": 170}, {"hour": 32.47, "karma": 169}, {"hour": 33.47, "karma": 171}, {"hour": 34.47, "karma": 171}, {"hour": 35.47, "karma": 168}, {"hour": 36.47, "karma": 170}, {"hour": 37.47, "karma": 176}, {"hour": 38.47, "karma": 177}, {"hour": 39.47, "karma": 176}, {"hour": 40.47, "karma": 180}, {"hour": 41.47, "karma": 177}, {"hour": 42.47, "karma": 181}, {"hour": 43.47, "karma": 175}, {"hour": 44.47, "karma": 174}, {"hour": 45.47, "karma": 175}, {"hour": 46.47, "karma": 173}, {"hour": 47.47, "karma": 178}]}, {"mal_id": 58600, "progression": [{"hour": 30.87, "karma": 328}, {"hour": 47.87, "karma": 345}]}, {"mal_id": 59265, "progression": [{"hour": 30.92, "karma": 149}, {"hour": 47.92, "karma": 154}]}, {"mal_id": 58271, "progression": [{"hour": 30.97, "karma": 281}, {"hour": 47.97, "karma": 299}]}, {"mal_id": 51119, "progression": [{"hour": 31.43, "karma": 42}]}, {"mal_id": 58822, "progression": [{"hour": 31.93, "karma": 159}]}, {"mal_id": 54857, "progression": [{"hour": 33.37, "karma": 3326}]}, {"mal_id": 58484, "progression": [{"hour": 33.97, "karma": 253}]}, {"mal_id": 57066, "progression": [{"hour": 34.97, "karma": 1184}]}, {"mal_id": 58199, "progression": [{"hour": 36.16, "karma": 19}]}, {"mal_id": 57554, "progression": [{"hour": 5.83, "karma": 66}]}, {"mal_id": 58259, "progression": [{"hour": 7.93, "karma": 22}]}, {"mal_id": 54769, "progression": [{"hour": 7.93, "karma": 1}]}, {"mal_id": 58739, "progression": [{"hour": 8.93, "karma": 55}]}, {"mal_id": 57719, "progression": [{"hour": 8.93, "karma": 300}]}, {"mal_id": 56653, "progression": [{"hour": 8.97, "karma": 327}]}, {"mal_id": 57592, "progression": [{"hour": 9.93, "karma": 470}]}, {"mal_id": 59144, "progression": [{"hour": 10.43, "karma": 30}]}, {"mal_id": 59561, "progression": [{"hour": 11.47, "karma": 121}]}, {"mal_id": 58600, "progression": [{"hour": 31.87, "karma": 330}]}, {"mal_id": 59265, "progression": [{"hour": 31.92, "karma": 151}]}, {"mal_id": 58271, "progression": [{"hour": 31.97, "karma": 282}]}, {"mal_id": 51119, "progression": [{"hour": 32.42, "karma": 42}]}, {"mal_id": 58822, "progression": [{"hour": 32.92, "karma": 164}]}, {"mal_id": 54857, "progression": [{"hour": 34.37, "karma": 3350}]}, {"mal_id": 58484, "progression": [{"hour": 34.97, "karma": 255}]}, {"mal_id": 57066, "progression": [{"hour": 35.97, "karma": 1189}]}, {"mal_id": 58199, "progression": [{"hour": 37.16, "karma": 19}]}, {"mal_id": 57554, "progression": [{"hour": 6.83, "karma": 81}]}, {"mal_id": 58259, "progression": [{"hour": 8.93, "karma": 22}]}, {"mal_id": 54769, "progression": [{"hour": 8.93, "karma": 3}]}, {"mal_id": 58739, "progression": [{"hour": 9.93, "karma": 66}]}, {"mal_id": 57719, "progression": [{"hour": 9.93, "karma": 323}]}, {"mal_id": 56653, "progression": [{"hour": 9.97, "karma": 352}]}, {"mal_id": 57592, "progression": [{"hour": 10.93, "karma": 500}]}, {"mal_id": 59144, "progression": [{"hour": 11.43, "karma": 29}]}, {"mal_id": 59561, "progression": [{"hour": 12.47, "karma": 128}]}, {"mal_id": 58600, "progression": [{"hour": 32.87, "karma": 330}]}, {"mal_id": 59265, "progression": [{"hour": 32.92, "karma": 151}]}, {"mal_id": 58271, "progression": [{"hour": 32.97, "karma": 283}]}, {"mal_id": 51119, "progression": [{"hour": 33.42, "karma": 44}]}, {"mal_id": 58822, "progression": [{"hour": 33.93, "karma": 158}]}, {"mal_id": 54857, "progression": [{"hour": 35.37, "karma": 3366}]}, {"mal_id": 58484, "progression": [{"hour": 35.97, "karma": 257}]}, {"mal_id": 57066, "progression": [{"hour": 36.97, "karma": 1198}]}, {"mal_id": 58199, "progression": [{"hour": 38.16, "karma": 20}]}, {"mal_id": 57554, "progression": [{"hour": 7.83, "karma": 91}]}, {"mal_id": 58259, "progression": [{"hour": 9.93, "karma": 24}]}, {"mal_id": 54769, "progression": [{"hour": 9.93, "karma": 5}]}, {"mal_id": 58739, "progression": [{"hour": 10.93, "karma": 69}]}, {"mal_id": 57719, "progression": [{"hour": 10.93, "karma": 352}]}, {"mal_id": 56653, "progression": [{"hour": 10.97, "karma": 369}]}, {"mal_id": 57592, "progression": [{"hour": 11.93, "karma": 538}]}, {"mal_id": 59144, "progression": [{"hour": 12.43, "karma": 35}]}, {"mal_id": 59561, "progression": [{"hour": 13.47, "karma": 135}]}, {"mal_id": 58600, "progression": [{"hour": 33.87, "karma": 332}]}, {"mal_id": 59265, "progression": [{"hour": 33.92, "karma": 150}]}, {"mal_id": 58271, "progression": [{"hour": 33.97, "karma": 286}]}, {"mal_id": 51119, "progression": [{"hour": 34.42, "karma": 44}]}, {"mal_id": 58822, "progression": [{"hour": 34.93, "karma": 162}]}, {"mal_id": 54857, "progression": [{"hour": 36.37, "karma": 3378}]}, {"mal_id": 58484, "progression": [{"hour": 36.97, "karma": 260}]}, {"mal_id": 57066, "progression": [{"hour": 37.97, "karma": 1203}]}, {"mal_id": 58199, "progression": [{"hour": 39.16, "karma": 20}]}, {"mal_id": 57554, "progression": [{"hour": 8.83, "karma": 95}]}, {"mal_id": 58259, "progression": [{"hour": 10.93, "karma": 23}]}, {"mal_id": 54769, "progression": [{"hour": 10.93, "karma": 4}]}, {"mal_id": 58739, "progression": [{"hour": 11.93, "karma": 76}]}, {"mal_id": 57719, "progression": [{"hour": 11.93, "karma": 371}]}, {"mal_id": 56653, "progression": [{"hour": 11.97, "karma": 382}]}, {"mal_id": 57592, "progression": [{"hour": 12.93, "karma": 559}]}, {"mal_id": 59144, "progression": [{"hour": 13.43, "karma": 34}]}, {"mal_id": 59561, "progression": [{"hour": 14.47, "karma": 134}]}, {"mal_id": 58600, "progression": [{"hour": 34.87, "karma": 337}]}, {"mal_id": 59265, "progression": [{"hour": 34.92, "karma": 149}]}, {"mal_id": 58271, "progression": [{"hour": 34.97, "karma": 289}]}, {"mal_id": 51119, "progression": [{"hour": 35.42, "karma": 41}]}, {"mal_id": 58822, "progression": [{"hour": 35.93, "karma": 164}]}, {"mal_id": 54857, "progression": [{"hour": 37.37, "karma": 3391}]}, {"mal_id": 58484, "progression": [{"hour": 37.97, "karma": 261}]}, {"mal_id": 57066, "progression": [{"hour": 38.97, "karma": 1202}]}, {"mal_id": 58199, "progression": [{"hour": 40.16, "karma": 18}]}, {"mal_id": 57554, "progression": [{"hour": 9.83, "karma": 103}]}, {"mal_id": 58259, "progression": [{"hour": 11.93, "karma": 26}]}, {"mal_id": 54769, "progression": [{"hour": 11.93, "karma": 5}]}, {"mal_id": 58739, "progression": [{"hour": 12.93, "karma": 75}]}, {"mal_id": 57719, "progression": [{"hour": 12.93, "karma": 386}]}, {"mal_id": 56653, "progression": [{"hour": 12.97, "karma": 392}]}, {"mal_id": 57592, "progression": [{"hour": 13.93, "karma": 587}]}, {"mal_id": 59144, "progression": [{"hour": 14.43, "karma": 37}]}, {"mal_id": 59561, "progression": [{"hour": 15.47, "karma": 141}]}, {"mal_id": 58600, "progression": [{"hour": 35.87, "karma": 341}]}, {"mal_id": 59265, "progression": [{"hour": 35.92, "karma": 150}]}, {"mal_id": 58271, "progression": [{"hour": 35.97, "karma": 291}]}, {"mal_id": 51119, "progression": [{"hour": 36.43, "karma": 46}]}, {"mal_id": 58822, "progression": [{"hour": 36.93, "karma": 166}]}, {"mal_id": 54857, "progression": [{"hour": 38.37, "karma": 3402}]}, {"mal_id": 58484, "progression": [{"hour": 38.97, "karma": 262}]}, {"mal_id": 57066, "progression": [{"hour": 39.97, "karma": 1214}]}, {"mal_id": 58199, "progression": [{"hour": 41.16, "karma": 16}]}, {"mal_id": 57554, "progression": [{"hour": 10.83, "karma": 110}]}, {"mal_id": 58259, "progression": [{"hour": 12.93, "karma": 27}]}, {"mal_id": 54769, "progression": [{"hour": 12.93, "karma": 7}]}, {"mal_id": 58739, "progression": [{"hour": 13.93, "karma": 75}]}, {"mal_id": 57719, "progression": [{"hour": 13.93, "karma": 399}]}, {"mal_id": 56653, "progression": [{"hour": 13.97, "karma": 399}]}, {"mal_id": 57592, "progression": [{"hour": 14.93, "karma": 602}]}, {"mal_id": 59144, "progression": [{"hour": 15.43, "karma": 35}]}, {"mal_id": 59561, "progression": [{"hour": 16.47, "karma": 146}]}, {"mal_id": 58600, "progression": [{"hour": 36.87, "karma": 335}]}, {"mal_id": 59265, "progression": [{"hour": 36.92, "karma": 155}]}, {"mal_id": 58271, "progression": [{"hour": 36.97, "karma": 293}]}, {"mal_id": 51119, "progression": [{"hour": 37.42, "karma": 44}]}, {"mal_id": 58822, "progression": [{"hour": 37.93, "karma": 165}]}, {"mal_id": 54857, "progression": [{"hour": 39.37, "karma": 3424}]}, {"mal_id": 58484, "progression": [{"hour": 39.97, "karma": 263}]}, {"mal_id": 57066, "progression": [{"hour": 40.97, "karma": 1216}]}, {"mal_id": 58199, "progression": [{"hour": 42.16, "karma": 18}]}, {"mal_id": 57554, "progression": [{"hour": 11.83, "karma": 116}]}, {"mal_id": 58259, "progression": [{"hour": 13.93, "karma": 25}]}, {"mal_id": 54769, "progression": [{"hour": 13.93, "karma": 4}]}, {"mal_id": 58739, "progression": [{"hour": 14.93, "karma": 78}]}, {"mal_id": 57719, "progression": [{"hour": 14.93, "karma": 410}]}, {"mal_id": 56653, "progression": [{"hour": 14.97, "karma": 403}]}, {"mal_id": 57592, "progression": [{"hour": 15.93, "karma": 612}]}, {"mal_id": 59144, "progression": [{"hour": 16.43, "karma": 35}]}, {"mal_id": 59561, "progression": [{"hour": 17.47, "karma": 149}]}, {"mal_id": 58600, "progression": [{"hour": 37.87, "karma": 337}]}, {"mal_id": 59265, "progression": [{"hour": 37.92, "karma": 154}]}, {"mal_id": 58271, "progression": [{"hour": 37.97, "karma": 293}]}, {"mal_id": 51119, "progression": [{"hour": 38.42, "karma": 46}]}, {"mal_id": 58822, "progression": [{"hour": 38.93, "karma": 162}]}, {"mal_id": 54857, "progression": [{"hour": 40.37, "karma": 3428}]}, {"mal_id": 58484, "progression": [{"hour": 40.97, "karma": 265}]}, {"mal_id": 57066, "progression": [{"hour": 41.97, "karma": 1216}]}, {"mal_id": 58199, "progression": [{"hour": 43.16, "karma": 19}]}, {"mal_id": 57554, "progression": [{"hour": 12.83, "karma": 122}]}, {"mal_id": 58259, "progression": [{"hour": 14.93, "karma": 25}]}, {"mal_id": 54769, "progression": [{"hour": 14.93, "karma": 4}]}, {"mal_id": 58739, "progression": [{"hour": 15.93, "karma": 75}]}, {"mal_id": 57719, "progression": [{"hour": 15.93, "karma": 410}]}, {"mal_id": 56653, "progression": [{"hour": 15.97, "karma": 413}]}, {"mal_id": 57592, "progression": [{"hour": 16.93, "karma": 626}]}, {"mal_id": 59144, "progression": [{"hour": 17.43, "karma": 36}]}, {"mal_id": 59561, "progression": [{"hour": 18.47, "karma": 150}]}, {"mal_id": 58600, "progression": [{"hour": 38.87, "karma": 346}]}, {"mal_id": 59265, "progression": [{"hour": 38.92, "karma": 152}]}, {"mal_id": 58271, "progression": [{"hour": 38.97, "karma": 298}]}, {"mal_id": 51119, "progression": [{"hour": 39.43, "karma": 45}]}, {"mal_id": 58822, "progression": [{"hour": 39.93, "karma": 167}]}, {"mal_id": 54857, "progression": [{"hour": 41.37, "karma": 3446}]}, {"mal_id": 58484, "progression": [{"hour": 41.97, "karma": 262}]}, {"mal_id": 57066, "progression": [{"hour": 42.97, "karma": 1223}]}, {"mal_id": 58199, "progression": [{"hour": 44.16, "karma": 20}]}, {"mal_id": 57554, "progression": [{"hour": 13.83, "karma": 124}]}, {"mal_id": 58259, "progression": [{"hour": 15.93, "karma": 24}]}, {"mal_id": 54769, "progression": [{"hour": 15.93, "karma": 6}]}, {"mal_id": 58739, "progression": [{"hour": 16.93, "karma": 76}]}, {"mal_id": 57719, "progression": [{"hour": 16.93, "karma": 428}]}, {"mal_id": 56653, "progression": [{"hour": 16.97, "karma": 424}]}, {"mal_id": 57592, "progression": [{"hour": 17.93, "karma": 638}]}, {"mal_id": 59144, "progression": [{"hour": 18.43, "karma": 45}]}, {"mal_id": 59561, "progression": [{"hour": 19.47, "karma": 155}]}, {"mal_id": 58600, "progression": [{"hour": 39.87, "karma": 340}]}, {"mal_id": 59265, "progression": [{"hour": 39.92, "karma": 152}]}, {"mal_id": 58271, "progression": [{"hour": 39.97, "karma": 293}]}, {"mal_id": 51119, "progression": [{"hour": 40.42, "karma": 46}]}, {"mal_id": 58822, "progression": [{"hour": 40.92, "karma": 163}]}, {"mal_id": 54857, "progression": [{"hour": 42.37, "karma": 3453}]}, {"mal_id": 58484, "progression": [{"hour": 42.97, "karma": 269}]}, {"mal_id": 57066, "progression": [{"hour": 43.97, "karma": 1231}]}, {"mal_id": 58199, "progression": [{"hour": 45.16, "karma": 18}]}, {"mal_id": 57554, "progression": [{"hour": 14.83, "karma": 127}]}, {"mal_id": 58259, "progression": [{"hour": 16.93, "karma": 25}]}, {"mal_id": 54769, "progression": [{"hour": 16.93, "karma": 5}]}, {"mal_id": 58739, "progression": [{"hour": 17.93, "karma": 81}]}, {"mal_id": 57719, "progression": [{"hour": 17.93, "karma": 433}]}, {"mal_id": 56653, "progression": [{"hour": 17.97, "karma": 434}]}, {"mal_id": 57592, "progression": [{"hour": 18.93, "karma": 658}]}, {"mal_id": 59144, "progression": [{"hour": 19.43, "karma": 45}]}, {"mal_id": 59561, "progression": [{"hour": 20.47, "karma": 154}]}, {"mal_id": 58600, "progression": [{"hour": 40.87, "karma": 344}]}, {"mal_id": 59265, "progression": [{"hour": 40.92, "karma": 151}]}, {"mal_id": 58271, "progression": [{"hour": 40.97, "karma": 296}]}, {"mal_id": 51119, "progression": [{"hour": 41.42, "karma": 46}]}, {"mal_id": 58822, "progression": [{"hour": 41.93, "karma": 169}]}, {"mal_id": 54857, "progression": [{"hour": 43.37, "karma": 3456}]}, {"mal_id": 58484, "progression": [{"hour": 43.97, "karma": 269}]}, {"mal_id": 57066, "progression": [{"hour": 44.97, "karma": 1233}]}, {"mal_id": 58199, "progression": [{"hour": 46.16, "karma": 20}]}, {"mal_id": 57554, "progression": [{"hour": 15.83, "karma": 130}]}, {"mal_id": 58259, "progression": [{"hour": 17.93, "karma": 26}]}, {"mal_id": 54769, "progression": [{"hour": 17.93, "karma": 6}]}, {"mal_id": 58739, "progression": [{"hour": 18.93, "karma": 82}]}, {"mal_id": 57719, "progression": [{"hour": 18.93, "karma": 434}]}, {"mal_id": 56653, "progression": [{"hour": 18.97, "karma": 433}]}, {"mal_id": 57592, "progression": [{"hour": 19.93, "karma": 656}]}, {"mal_id": 59144, "progression": [{"hour": 20.43, "karma": 43}]}, {"mal_id": 59561, "progression": [{"hour": 21.47, "karma": 158}]}, {"mal_id": 58600, "progression": [{"hour": 41.87, "karma": 347}]}, {"mal_id": 59265, "progression": [{"hour": 41.92, "karma": 151}]}, {"mal_id": 58271, "progression": [{"hour": 41.97, "karma": 300}]}, {"mal_id": 51119, "progression": [{"hour": 42.42, "karma": 43}]}, {"mal_id": 58822, "progression": [{"hour": 42.93, "karma": 167}]}, {"mal_id": 54857, "progression": [{"hour": 44.37, "karma": 3468}]}, {"mal_id": 58484, "progression": [{"hour": 44.97, "karma": 267}]}, {"mal_id": 57066, "progression": [{"hour": 45.97, "karma": 1230}]}, {"mal_id": 58199, "progression": [{"hour": 47.16, "karma": 19}]}, {"mal_id": 57554, "progression": [{"hour": 16.83, "karma": 126}]}, {"mal_id": 58259, "progression": [{"hour": 18.93, "karma": 26}]}, {"mal_id": 54769, "progression": [{"hour": 18.93, "karma": 5}]}, {"mal_id": 58739, "progression": [{"hour": 19.93, "karma": 86}]}, {"mal_id": 57719, "progression": [{"hour": 19.93, "karma": 435}]}, {"mal_id": 56653, "progression": [{"hour": 19.97, "karma": 432}]}, {"mal_id": 57592, "progression": [{"hour": 20.93, "karma": 664}]}, {"mal_id": 59144, "progression": [{"hour": 21.43, "karma": 45}]}, {"mal_id": 59561, "progression": [{"hour": 22.47, "karma": 159}]}, {"mal_id": 58600, "progression": [{"hour": 42.87, "karma": 343}]}, {"mal_id": 59265, "progression": [{"hour": 42.92, "karma": 153}]}, {"mal_id": 58271, "progression": [{"hour": 42.97, "karma": 300}]}, {"mal_id": 51119, "progression": [{"hour": 43.42, "karma": 47}]}, {"mal_id": 58822, "progression": [{"hour": 43.93, "karma": 170}]}, {"mal_id": 54857, "progression": [{"hour": 45.37, "karma": 3463}]}, {"mal_id": 58484, "progression": [{"hour": 45.97, "karma": 269}]}, {"mal_id": 57066, "progression": [{"hour": 46.97, "karma": 1236}]}, {"mal_id": 57554, "progression": [{"hour": 17.83, "karma": 131}]}, {"mal_id": 58259, "progression": [{"hour": 19.93, "karma": 26}]}, {"mal_id": 54769, "progression": [{"hour": 19.93, "karma": 5}]}, {"mal_id": 58739, "progression": [{"hour": 20.93, "karma": 81}]}, {"mal_id": 57719, "progression": [{"hour": 20.93, "karma": 447}]}, {"mal_id": 56653, "progression": [{"hour": 20.97, "karma": 439}]}, {"mal_id": 57592, "progression": [{"hour": 21.93, "karma": 673}]}, {"mal_id": 59144, "progression": [{"hour": 22.43, "karma": 47}]}, {"mal_id": 59561, "progression": [{"hour": 23.47, "karma": 160}]}, {"mal_id": 58600, "progression": [{"hour": 43.87, "karma": 343}]}, {"mal_id": 59265, "progression": [{"hour": 43.92, "karma": 156}]}, {"mal_id": 58271, "progression": [{"hour": 43.97, "karma": 301}]}, {"mal_id": 51119, "progression": [{"hour": 44.43, "karma": 44}]}, {"mal_id": 58822, "progression": [{"hour": 44.93, "karma": 167}]}, {"mal_id": 54857, "progression": [{"hour": 46.37, "karma": 3468}]}, {"mal_id": 58484, "progression": [{"hour": 46.97, "karma": 269}]}, {"mal_id": 57066, "progression": [{"hour": 47.97, "karma": 1237}]}, {"mal_id": 57554, "progression": [{"hour": 18.83, "karma": 130}]}, {"mal_id": 58259, "progression": [{"hour": 20.93, "karma": 27}]}, {"mal_id": 54769, "progression": [{"hour": 20.93, "karma": 8}]}, {"mal_id": 58739, "progression": [{"hour": 21.93, "karma": 85}]}, {"mal_id": 57719, "progression": [{"hour": 21.93, "karma": 452}]}, {"mal_id": 56653, "progression": [{"hour": 21.97, "karma": 443}]}, {"mal_id": 57592, "progression": [{"hour": 22.93, "karma": 684}]}, {"mal_id": 59144, "progression": [{"hour": 23.43, "karma": 50}]}, {"mal_id": 59561, "progression": [{"hour": 24.47, "karma": 163}]}, {"mal_id": 58600, "progression": [{"hour": 44.87, "karma": 345}]}, {"mal_id": 59265, "progression": [{"hour": 44.92, "karma": 152}]}, {"mal_id": 58271, "progression": [{"hour": 44.97, "karma": 300}]}, {"mal_id": 51119, "progression": [{"hour": 45.42, "karma": 46}]}, {"mal_id": 58822, "progression": [{"hour": 45.92, "karma": 170}]}, {"mal_id": 54857, "progression": [{"hour": 47.37, "karma": 3480}]}, {"mal_id": 58484, "progression": [{"hour": 47.97, "karma": 270}]}, {"mal_id": 59136, "progression": [{"hour": 0.43, "karma": 6}, {"hour": 2.43, "karma": 33}, {"hour": 3.43, "karma": 42}, {"hour": 4.43, "karma": 62}, {"hour": 5.43, "karma": 67}, {"hour": 6.43, "karma": 71}, {"hour": 7.43, "karma": 75}, {"hour": 8.43, "karma": 84}, {"hour": 9.43, "karma": 88}, {"hour": 10.43, "karma": 93}, {"hour": 11.43, "karma": 98}, {"hour": 12.43, "karma": 106}, {"hour": 13.43, "karma": 108}, {"hour": 14.43, "karma": 115}, {"hour": 15.43, "karma": 119}, {"hour": 16.43, "karma": 119}, {"hour": 17.43, "karma": 119}, {"hour": 18.43, "karma": 122}, {"hour": 19.43, "karma": 121}, {"hour": 20.43, "karma": 124}, {"hour": 21.43, "karma": 128}, {"hour": 22.43, "karma": 125}, {"hour": 23.43, "karma": 125}, {"hour": 24.43, "karma": 121}, {"hour": 30.43, "karma": 126}, {"hour": 30.75, "karma": 130}, {"hour": 31.43, "karma": 129}, {"hour": 32.43, "karma": 131}, {"hour": 33.43, "karma": 131}, {"hour": 34.43, "karma": 135}, {"hour": 35.43, "karma": 132}, {"hour": 36.12, "karma": 137}, {"hour": 36.2, "karma": 134}, {"hour": 36.26, "karma": 131}, {"hour": 36.43, "karma": 133}, {"hour": 36.76, "karma": 137}, {"hour": 37.43, "karma": 135}, {"hour": 38.43, "karma": 136}, {"hour": 39.43, "karma": 136}, {"hour": 40.43, "karma": 135}, {"hour": 42.43, "karma": 136}, {"hour": 43.43, "karma": 135}, {"hour": 44.43, "karma": 134}, {"hour": 45.43, "karma": 135}, {"hour": 46.43, "karma": 135}, {"hour": 46.46, "karma": 138}, {"hour": 47.43, "karma": 138}]}, {"mal_id": 57648, "progression": [{"hour": 0.93, "karma": 6}, {"hour": 2.93, "karma": 79}, {"hour": 3.93, "karma": 113}, {"hour": 4.93, "karma": 138}, {"hour": 5.93, "karma": 152}, {"hour": 6.93, "karma": 166}, {"hour": 7.93, "karma": 174}, {"hour": 8.93, "karma": 197}, {"hour": 9.93, "karma": 207}, {"hour": 10.93, "karma": 212}, {"hour": 11.93, "karma": 228}, {"hour": 12.93, "karma": 246}, {"hour": 13.93, "karma": 247}, {"hour": 14.93, "karma": 252}, {"hour": 15.93, "karma": 260}, {"hour": 16.93, "karma": 260}, {"hour": 17.93, "karma": 268}, {"hour": 18.93, "karma": 268}, {"hour": 19.93, "karma": 273}, {"hour": 20.93, "karma": 274}, {"hour": 21.93, "karma": 288}, {"hour": 22.93, "karma": 290}, {"hour": 23.93, "karma": 293}, {"hour": 24.93, "karma": 298}, {"hour": 30.93, "karma": 310}, {"hour": 31.25, "karma": 314}, {"hour": 31.93, "karma": 312}, {"hour": 32.93, "karma": 315}, {"hour": 33.93, "karma": 313}, {"hour": 34.93, "karma": 314}, {"hour": 35.93, "karma": 319}, {"hour": 36.62, "karma": 321}, {"hour": 36.7, "karma": 322}, {"hour": 36.76, "karma": 322}, {"hour": 36.93, "karma": 322}, {"hour": 37.26, "karma": 323}, {"hour": 37.93, "karma": 322}, {"hour": 38.93, "karma": 324}, {"hour": 39.93, "karma": 320}, {"hour": 40.93, "karma": 325}, {"hour": 42.93, "karma": 329}, {"hour": 43.93, "karma": 326}, {"hour": 44.93, "karma": 329}, {"hour": 45.93, "karma": 329}, {"hour": 46.93, "karma": 330}, {"hour": 46.96, "karma": 329}, {"hour": 47.93, "karma": 329}]}, {"mal_id": 57554, "progression": [{"hour": 19.83, "karma": 131}]}, {"mal_id": 58259, "progression": [{"hour": 21.93, "karma": 30}]}, {"mal_id": 54769, "progression": [{"hour": 21.93, "karma": 7}]}, {"mal_id": 58739, "progression": [{"hour": 22.93, "karma": 89}]}, {"mal_id": 57719, "progression": [{"hour": 22.93, "karma": 466}]}, {"mal_id": 56653, "progression": [{"hour": 22.97, "karma": 447}]}, {"mal_id": 57592, "progression": [{"hour": 23.93, "karma": 693}]}, {"mal_id": 59144, "progression": [{"hour": 24.43, "karma": 49}]}, {"mal_id": 59561, "progression": [{"hour": 25.47, "karma": 166}]}, {"mal_id": 58600, "progression": [{"hour": 45.87, "karma": 347}]}, {"mal_id": 59265, "progression": [{"hour": 45.92, "karma": 151}]}, {"mal_id": 58271, "progression": [{"hour": 45.97, "karma": 302}]}, {"mal_id": 51119, "progression": [{"hour": 46.42, "karma": 47}]}, {"mal_id": 58822, "progression": [{"hour": 46.93, "karma": 169}]}, {"mal_id": 59113, "progression": [{"hour": 0.47, "karma": 1}, {"hour": 1.47, "karma": 1}, {"hour": 2.47, "karma": 1}, {"hour": 3.47, "karma": 4}, {"hour": 4.47, "karma": 5}, {"hour": 5.47, "karma": 3}, {"hour": 6.47, "karma": 5}, {"hour": 7.47, "karma": 4}, {"hour": 8.47, "karma": 4}, {"hour": 9.47, "karma": 9}, {"hour": 10.47, "karma": 7}, {"hour": 11.47, "karma": 9}, {"hour": 12.47, "karma": 6}, {"hour": 13.47, "karma": 6}, {"hour": 14.47, "karma": 10}, {"hour": 15.47, "karma": 10}, {"hour": 16.47, "karma": 9}, {"hour": 17.47, "karma": 9}, {"hour": 18.47, "karma": 12}, {"hour": 19.47, "karma": 9}, {"hour": 20.47, "karma": 10}, {"hour": 21.47, "karma": 13}, {"hour": 22.47, "karma": 12}, {"hour": 23.47, "karma": 11}, {"hour": 29.47, "karma": 12}, {"hour": 29.79, "karma": 12}, {"hour": 30.47, "karma": 11}, {"hour": 31.47, "karma": 11}, {"hour": 32.47, "karma": 10}, {"hour": 33.47, "karma": 12}, {"hour": 34.47, "karma": 11}, {"hour": 35.17, "karma": 12}, {"hour": 35.25, "karma": 11}, {"hour": 35.31, "karma": 11}, {"hour": 35.47, "karma": 12}, {"hour": 35.8, "karma": 10}, {"hour": 36.47, "karma": 12}, {"hour": 37.47, "karma": 14}, {"hour": 38.47, "karma": 11}, {"hour": 39.47, "karma": 13}, {"hour": 41.47, "karma": 11}, {"hour": 42.47, "karma": 13}, {"hour": 43.47, "karma": 12}, {"hour": 44.47, "karma": 11}, {"hour": 45.47, "karma": 14}, {"hour": 45.5, "karma": 13}, {"hour": 46.47, "karma": 16}, {"hour": 47.47, "karma": 14}]}, {"mal_id": 58514, "progression": [{"hour": 0.93, "karma": 121}, {"hour": 1.93, "karma": 250}, {"hour": 2.93, "karma": 425}, {"hour": 3.93, "karma": 629}, {"hour": 4.93, "karma": 790}, {"hour": 5.93, "karma": 936}, {"hour": 6.93, "karma": 1077}, {"hour": 7.93, "karma": 1217}, {"hour": 8.93, "karma": 1344}, {"hour": 9.93, "karma": 1456}, {"hour": 10.93, "karma": 1563}, {"hour": 11.93, "karma": 1660}, {"hour": 12.93, "karma": 1733}, {"hour": 13.93, "karma": 1783}, {"hour": 14.93, "karma": 1853}, {"hour": 15.93, "karma": 1904}, {"hour": 16.93, "karma": 1949}, {"hour": 17.93, "karma": 1993}, {"hour": 18.93, "karma": 2031}, {"hour": 19.93, "karma": 2063}, {"hour": 20.93, "karma": 2093}, {"hour": 21.93, "karma": 2117}, {"hour": 22.93, "karma": 2150}, {"hour": 23.93, "karma": 2180}, {"hour": 29.93, "karma": 2340}, {"hour": 30.25, "karma": 2352}, {"hour": 30.93, "karma": 2355}, {"hour": 31.93, "karma": 2375}, {"hour": 32.93, "karma": 2397}, {"hour": 33.93, "karma": 2408}, {"hour": 34.93, "karma": 2426}, {"hour": 35.62, "karma": 2432}, {"hour": 35.7, "karma": 2438}, {"hour": 35.76, "karma": 2434}, {"hour": 35.93, "karma": 2439}, {"hour": 36.26, "karma": 2438}, {"hour": 36.93, "karma": 2448}, {"hour": 37.93, "karma": 2464}, {"hour": 38.93, "karma": 2471}, {"hour": 39.93, "karma": 2483}, {"hour": 41.93, "karma": 2500}, {"hour": 42.93, "karma": 2509}, {"hour": 43.93, "karma": 2509}, {"hour": 44.93, "karma": 2519}, {"hour": 45.93, "karma": 2524}, {"hour": 45.96, "karma": 2522}, {"hour": 46.93, "karma": 2532}, {"hour": 47.93, "karma": 2541}]}, {"mal_id": 59136, "progression": [{"hour": 1.43, "karma": 22}]}, {"mal_id": 57648, "progression": [{"hour": 1.93, "karma": 39}]}, {"mal_id": 57554, "progression": [{"hour": 20.83, "karma": 138}]}, {"mal_id": 58259, "progression": [{"hour": 22.93, "karma": 29}]}, {"mal_id": 54769, "progression": [{"hour": 22.93, "karma": 6}]}, {"mal_id": 58739, "progression": [{"hour": 23.93, "karma": 85}]}, {"mal_id": 57719, "progression": [{"hour": 23.93, "karma": 467}]}, {"mal_id": 56653, "progression": [{"hour": 23.97, "karma": 446}]}, {"mal_id": 57592, "progression": [{"hour": 24.93, "karma": 703}]}, {"mal_id": 59144, "progression": [{"hour": 25.43, "karma": 49}]}, {"mal_id": 59561, "progression": [{"hour": 26.47, "karma": 164}]}, {"mal_id": 58600, "progression": [{"hour": 46.87, "karma": 352}]}, {"mal_id": 59265, "progression": [{"hour": 46.92, "karma": 155}]}, {"mal_id": 58271, "progression": [{"hour": 46.97, "karma": 298}]}, {"mal_id": 51119, "progression": [{"hour": 47.43, "karma": 45}]}, {"mal_id": 58822, "progression": [{"hour": 47.93, "karma": 166}]}, {"mal_id": 55997, "progression": [{"hour": 0.43, "karma": 24}, {"hour": 1.43, "karma": 68}, {"hour": 2.43, "karma": 118}, {"hour": 3.43, "karma": 152}, {"hour": 4.43, "karma": 192}, {"hour": 5.43, "karma": 240}, {"hour": 6.43, "karma": 282}, {"hour": 7.43, "karma": 309}, {"hour": 8.43, "karma": 336}, {"hour": 9.43, "karma": 360}, {"hour": 10.43, "karma": 386}, {"hour": 11.43, "karma": 402}, {"hour": 12.43, "karma": 420}, {"hour": 13.43, "karma": 427}, {"hour": 14.43, "karma": 447}, {"hour": 15.43, "karma": 454}, {"hour": 16.43, "karma": 465}, {"hour": 17.43, "karma": 477}, {"hour": 18.43, "karma": 483}, {"hour": 19.43, "karma": 486}, {"hour": 20.43, "karma": 491}, {"hour": 21.43, "karma": 506}, {"hour": 22.43, "karma": 508}, {"hour": 28.43, "karma": 535}, {"hour": 28.75, "karma": 538}, {"hour": 29.43, "karma": 532}, {"hour": 30.43, "karma": 533}, {"hour": 31.43, "karma": 542}, {"hour": 32.43, "karma": 545}, {"hour": 33.43, "karma": 547}, {"hour": 34.12, "karma": 548}, {"hour": 34.2, "karma": 545}, {"hour": 34.26, "karma": 547}, {"hour": 34.43, "karma": 549}, {"hour": 34.76, "karma": 551}, {"hour": 35.43, "karma": 550}, {"hour": 36.43, "karma": 556}, {"hour": 37.43, "karma": 554}, {"hour": 38.43, "karma": 555}, {"hour": 40.43, "karma": 556}, {"hour": 41.43, "karma": 567}, {"hour": 42.43, "karma": 557}, {"hour": 43.43, "karma": 564}, {"hour": 44.43, "karma": 566}, {"hour": 44.46, "karma": 566}, {"hour": 45.43, "karma": 564}, {"hour": 46.43, "karma": 569}, {"hour": 47.43, "karma": 569}]}, {"mal_id": 58216, "progression": [{"hour": 0.43, "karma": 5}, {"hour": 1.43, "karma": 7}, {"hour": 2.43, "karma": 19}, {"hour": 3.43, "karma": 26}, {"hour": 4.43, "karma": 28}, {"hour": 5.43, "karma": 37}, {"hour": 6.43, "karma": 39}, {"hour": 7.43, "karma": 40}, {"hour": 8.43, "karma": 44}, {"hour": 9.43, "karma": 42}, {"hour": 10.43, "karma": 52}, {"hour": 11.43, "karma": 50}, {"hour": 12.43, "karma": 54}, {"hour": 13.43, "karma": 60}, {"hour": 14.43, "karma": 58}, {"hour": 15.43, "karma": 55}, {"hour": 16.43, "karma": 59}, {"hour": 17.43, "karma": 60}, {"hour": 18.43, "karma": 57}, {"hour": 19.43, "karma": 62}, {"hour": 20.43, "karma": 61}, {"hour": 21.43, "karma": 58}, {"hour": 22.43, "karma": 63}, {"hour": 28.43, "karma": 66}, {"hour": 28.75, "karma": 63}, {"hour": 29.43, "karma": 61}, {"hour": 30.43, "karma": 64}, {"hour": 31.43, "karma": 63}, {"hour": 32.43, "karma": 67}, {"hour": 33.43, "karma": 69}, {"hour": 34.12, "karma": 65}, {"hour": 34.2, "karma": 64}, {"hour": 34.26, "karma": 65}, {"hour": 34.43, "karma": 69}, {"hour": 34.76, "karma": 65}, {"hour": 35.43, "karma": 67}, {"hour": 36.43, "karma": 67}, {"hour": 37.43, "karma": 68}, {"hour": 38.43, "karma": 71}, {"hour": 40.43, "karma": 67}, {"hour": 41.43, "karma": 69}, {"hour": 42.43, "karma": 67}, {"hour": 43.43, "karma": 66}, {"hour": 44.43, "karma": 66}, {"hour": 44.46, "karma": 68}, {"hour": 45.43, "karma": 67}, {"hour": 46.43, "karma": 65}, {"hour": 47.43, "karma": 65}]}, {"mal_id": 59135, "progression": [{"hour": 0.93, "karma": 18}, {"hour": 1.93, "karma": 47}, {"hour": 2.93, "karma": 77}, {"hour": 3.93, "karma": 100}, {"hour": 4.93, "karma": 118}, {"hour": 5.93, "karma": 132}, {"hour": 6.93, "karma": 156}, {"hour": 7.93, "karma": 159}, {"hour": 8.93, "karma": 167}, {"hour": 9.93, "karma": 179}, {"hour": 10.93, "karma": 195}, {"hour": 11.93, "karma": 203}, {"hour": 12.93, "karma": 206}, {"hour": 13.93, "karma": 206}, {"hour": 14.93, "karma": 214}, {"hour": 15.93, "karma": 220}, {"hour": 16.93, "karma": 222}, {"hour": 17.93, "karma": 231}, {"hour": 18.93, "karma": 231}, {"hour": 19.93, "karma": 236}, {"hour": 20.93, "karma": 246}, {"hour": 21.93, "karma": 246}, {"hour": 22.93, "karma": 247}, {"hour": 28.93, "karma": 265}, {"hour": 29.25, "karma": 259}, {"hour": 29.93, "karma": 266}, {"hour": 30.93, "karma": 266}, {"hour": 31.93, "karma": 267}, {"hour": 32.93, "karma": 266}, {"hour": 33.93, "karma": 267}, {"hour": 34.62, "karma": 268}, {"hour": 34.7, "karma": 270}, {"hour": 34.76, "karma": 269}, {"hour": 34.93, "karma": 268}, {"hour": 35.26, "karma": 273}, {"hour": 35.93, "karma": 275}, {"hour": 36.93, "karma": 275}, {"hour": 37.93, "karma": 277}, {"hour": 38.93, "karma": 273}, {"hour": 40.93, "karma": 279}, {"hour": 41.93, "karma": 280}, {"hour": 42.93, "karma": 277}, {"hour": 43.93, "karma": 277}, {"hour": 44.93, "karma": 279}, {"hour": 44.96, "karma": 280}, {"hour": 45.93, "karma": 277}, {"hour": 46.93, "karma": 275}, {"hour": 47.93, "karma": 277}]}, {"mal_id": 58066, "progression": [{"hour": 0.93, "karma": 24}, {"hour": 1.93, "karma": 39}, {"hour": 2.93, "karma": 56}, {"hour": 3.93, "karma": 68}, {"hour": 4.93, "karma": 87}, {"hour": 5.93, "karma": 93}, {"hour": 6.93, "karma": 106}, {"hour": 7.93, "karma": 111}, {"hour": 8.93, "karma": 116}, {"hour": 9.93, "karma": 121}, {"hour": 10.93, "karma": 128}, {"hour": 11.93, "karma": 129}, {"hour": 12.93, "karma": 133}, {"hour": 13.93, "karma": 141}, {"hour": 14.93, "karma": 139}, {"hour": 15.93, "karma": 148}, {"hour": 16.93, "karma": 141}, {"hour": 17.93, "karma": 148}, {"hour": 18.93, "karma": 150}, {"hour": 19.93, "karma": 152}, {"hour": 20.93, "karma": 153}, {"hour": 21.93, "karma": 156}, {"hour": 27.93, "karma": 164}, {"hour": 28.25, "karma": 157}, {"hour": 28.93, "karma": 162}, {"hour": 29.93, "karma": 160}, {"hour": 30.93, "karma": 161}, {"hour": 31.93, "karma": 162}, {"hour": 32.93, "karma": 159}, {"hour": 33.62, "karma": 161}, {"hour": 33.7, "karma": 165}, {"hour": 33.76, "karma": 161}, {"hour": 33.93, "karma": 164}, {"hour": 34.26, "karma": 161}, {"hour": 34.93, "karma": 164}, {"hour": 35.93, "karma": 162}, {"hour": 36.93, "karma": 163}, {"hour": 37.93, "karma": 164}, {"hour": 39.93, "karma": 165}, {"hour": 40.93, "karma": 162}, {"hour": 41.93, "karma": 160}, {"hour": 42.93, "karma": 165}, {"hour": 43.93, "karma": 166}, {"hour": 43.96, "karma": 166}, {"hour": 44.93, "karma": 167}, {"hour": 45.93, "karma": 168}, {"hour": 46.93, "karma": 166}, {"hour": 47.93, "karma": 164}]}, {"mal_id": 57181, "progression": [{"hour": 0.93, "karma": 30}, {"hour": 1.93, "karma": 55}, {"hour": 2.93, "karma": 76}, {"hour": 3.93, "karma": 105}, {"hour": 4.93, "karma": 130}, {"hour": 5.93, "karma": 152}, {"hour": 6.93, "karma": 171}, {"hour": 7.93, "karma": 187}, {"hour": 8.93, "karma": 209}, {"hour": 9.93, "karma": 223}, {"hour": 10.93, "karma": 235}, {"hour": 11.93, "karma": 253}, {"hour": 12.93, "karma": 271}, {"hour": 13.93, "karma": 283}, {"hour": 14.93, "karma": 289}, {"hour": 15.93, "karma": 296}, {"hour": 16.93, "karma": 320}, {"hour": 17.93, "karma": 330}, {"hour": 23.93, "karma": 391}, {"hour": 24.25, "karma": 396}, {"hour": 24.93, "karma": 399}, {"hour": 25.93, "karma": 394}, {"hour": 26.93, "karma": 404}, {"hour": 27.93, "karma": 412}, {"hour": 28.93, "karma": 411}, {"hour": 29.62, "karma": 411}, {"hour": 29.7, "karma": 411}, {"hour": 29.76, "karma": 408}, {"hour": 29.93, "karma": 412}, {"hour": 30.26, "karma": 415}, {"hour": 30.93, "karma": 414}, {"hour": 31.93, "karma": 423}, {"hour": 32.93, "karma": 422}, {"hour": 33.93, "karma": 423}, {"hour": 35.93, "karma": 429}, {"hour": 36.93, "karma": 427}, {"hour": 37.93, "karma": 427}, {"hour": 38.93, "karma": 431}, {"hour": 39.93, "karma": 430}, {"hour": 39.96, "karma": 429}, {"hour": 40.93, "karma": 427}, {"hour": 41.93, "karma": 430}, {"hour": 42.93, "karma": 434}, {"hour": 43.93, "karma": 431}, {"hour": 44.93, "karma": 434}, {"hour": 45.93, "karma": 438}, {"hour": 46.93, "karma": 439}, {"hour": 47.93, "karma": 434}]}, {"mal_id": 54144, "progression": [{"hour": 0.97, "karma": 1}, {"hour": 1.97, "karma": 1}, {"hour": 2.97, "karma": 1}, {"hour": 3.97, "karma": 1}, {"hour": 4.97, "karma": 1}, {"hour": 5.97, "karma": 1}, {"hour": 6.97, "karma": 2}, {"hour": 7.97, "karma": 2}, {"hour": 8.97, "karma": 3}, {"hour": 9.97, "karma": 3}, {"hour": 10.97, "karma": 3}, {"hour": 11.97, "karma": 3}, {"hour": 12.97, "karma": 3}, {"hour": 13.97, "karma": 3}, {"hour": 14.97, "karma": 3}, {"hour": 15.97, "karma": 3}, {"hour": 21.97, "karma": 3}, {"hour": 22.29, "karma": 3}, {"hour": 22.97, "karma": 3}, {"hour": 23.97, "karma": 3}, {"hour": 24.97, "karma": 3}, {"hour": 25.97, "karma": 3}, {"hour": 26.97, "karma": 3}, {"hour": 27.66, "karma": 3}, {"hour": 27.74, "karma": 3}, {"hour": 27.8, "karma": 3}, {"hour": 27.97, "karma": 3}, {"hour": 28.3, "karma": 3}, {"hour": 28.97, "karma": 3}, {"hour": 29.97, "karma": 3}, {"hour": 30.97, "karma": 3}, {"hour": 31.97, "karma": 3}, {"hour": 33.97, "karma": 3}, {"hour": 34.97, "karma": 3}, {"hour": 35.97, "karma": 3}, {"hour": 36.97, "karma": 3}, {"hour": 37.97, "karma": 3}, {"hour": 38.0, "karma": 3}, {"hour": 38.97, "karma": 5}, {"hour": 39.97, "karma": 3}, {"hour": 40.97, "karma": 5}, {"hour": 41.97, "karma": 2}, {"hour": 42.97, "karma": 6}, {"hour": 43.97, "karma": 5}, {"hour": 44.97, "karma": 4}, {"hour": 45.97, "karma": 4}, {"hour": 46.97, "karma": 5}, {"hour": 47.97, "karma": 4}]}, {"mal_id": 56647, "progression": [{"hour": 0.93, "karma": 0}, {"hour": 1.93, "karma": 0}, {"hour": 2.93, "karma": 1}, {"hour": 3.93, "karma": 1}, {"hour": 9.93, "karma": 16}, {"hour": 10.25, "karma": 17}, {"hour": 10.93, "karma": 15}, {"hour": 11.93, "karma": 15}, {"hour": 12.93, "karma": 15}, {"hour": 13.93, "karma": 17}, {"hour": 14.93, "karma": 18}, {"hour": 15.62, "karma": 21}, {"hour": 15.7, "karma": 23}, {"hour": 15.76, "karma": 23}, {"hour": 15.93, "karma": 22}, {"hour": 16.26, "karma": 21}, {"hour": 16.93, "karma": 21}, {"hour": 17.93, "karma": 23}, {"hour": 18.93, "karma": 23}, {"hour": 19.93, "karma": 24}, {"hour": 21.93, "karma": 24}, {"hour": 22.93, "karma": 24}, {"hour": 23.93, "karma": 27}, {"hour": 24.93, "karma": 24}, {"hour": 25.93, "karma": 27}, {"hour": 25.96, "karma": 24}, {"hour": 26.93, "karma": 26}, {"hour": 27.93, "karma": 26}, {"hour": 28.93, "karma": 26}, {"hour": 29.93, "karma": 24}, {"hour": 30.93, "karma": 26}, {"hour": 31.93, "karma": 25}, {"hour": 32.93, "karma": 25}, {"hour": 33.93, "karma": 27}, {"hour": 34.93, "karma": 24}, {"hour": 35.93, "karma": 27}, {"hour": 36.93, "karma": 25}, {"hour": 37.93, "karma": 25}, {"hour": 38.93, "karma": 25}, {"hour": 39.93, "karma": 23}, {"hour": 40.93, "karma": 25}, {"hour": 41.93, "karma": 27}, {"hour": 42.93, "karma": 27}, {"hour": 43.93, "karma": 29}, {"hour": 44.93, "karma": 28}, {"hour": 45.93, "karma": 29}, {"hour": 46.93, "karma": 29}, {"hour": 47.93, "karma": 28}]}, {"mal_id": 58939, "progression": [{"hour": 0.42, "karma": 16}, {"hour": 6.42, "karma": 297}, {"hour": 6.74, "karma": 300}, {"hour": 7.42, "karma": 318}, {"hour": 8.42, "karma": 336}, {"hour": 9.42, "karma": 360}, {"hour": 10.42, "karma": 374}, {"hour": 11.42, "karma": 393}, {"hour": 12.12, "karma": 400}, {"hour": 12.2, "karma": 403}, {"hour": 12.26, "karma": 408}, {"hour": 12.42, "karma": 403}, {"hour": 12.75, "karma": 413}, {"hour": 13.42, "karma": 421}, {"hour": 14.42, "karma": 437}, {"hour": 15.42, "karma": 446}, {"hour": 16.42, "karma": 457}, {"hour": 18.42, "karma": 472}, {"hour": 19.42, "karma": 485}, {"hour": 20.42, "karma": 492}, {"hour": 21.42, "karma": 494}, {"hour": 22.42, "karma": 511}, {"hour": 22.46, "karma": 511}, {"hour": 23.42, "karma": 511}, {"hour": 24.42, "karma": 517}, {"hour": 25.42, "karma": 529}, {"hour": 26.42, "karma": 526}, {"hour": 27.42, "karma": 531}, {"hour": 28.42, "karma": 533}, {"hour": 29.42, "karma": 535}, {"hour": 30.42, "karma": 535}, {"hour": 31.42, "karma": 537}, {"hour": 32.42, "karma": 541}, {"hour": 33.42, "karma": 547}, {"hour": 34.42, "karma": 543}, {"hour": 35.42, "karma": 546}, {"hour": 36.42, "karma": 547}, {"hour": 37.42, "karma": 550}, {"hour": 38.42, "karma": 553}, {"hour": 39.42, "karma": 558}, {"hour": 40.42, "karma": 553}, {"hour": 41.42, "karma": 551}, {"hour": 42.42, "karma": 556}, {"hour": 43.42, "karma": 563}, {"hour": 44.42, "karma": 559}, {"hour": 45.42, "karma": 565}, {"hour": 46.42, "karma": 561}, {"hour": 47.42, "karma": 559}]}, {"mal_id": 58473, "progression": [{"hour": 0.92, "karma": 10}, {"hour": 6.92, "karma": 63}, {"hour": 7.24, "karma": 66}, {"hour": 7.92, "karma": 75}, {"hour": 8.92, "karma": 77}, {"hour": 9.92, "karma": 82}, {"hour": 10.92, "karma": 89}, {"hour": 11.92, "karma": 91}, {"hour": 12.62, "karma": 90}, {"hour": 12.7, "karma": 94}, {"hour": 12.76, "karma": 91}, {"hour": 12.92, "karma": 95}, {"hour": 13.25, "karma": 92}, {"hour": 13.92, "karma": 101}, {"hour": 14.92, "karma": 104}, {"hour": 15.92, "karma": 102}, {"hour": 16.92, "karma": 108}, {"hour": 18.92, "karma": 104}, {"hour": 19.92, "karma": 110}, {"hour": 20.92, "karma": 108}, {"hour": 21.92, "karma": 108}, {"hour": 22.92, "karma": 111}, {"hour": 22.96, "karma": 110}, {"hour": 23.92, "karma": 111}, {"hour": 24.92, "karma": 112}, {"hour": 25.92, "karma": 114}, {"hour": 26.92, "karma": 116}, {"hour": 27.92, "karma": 116}, {"hour": 28.92, "karma": 113}, {"hour": 29.92, "karma": 112}, {"hour": 30.92, "karma": 115}, {"hour": 31.92, "karma": 113}, {"hour": 32.92, "karma": 112}, {"hour": 33.92, "karma": 116}, {"hour": 34.92, "karma": 113}, {"hour": 35.92, "karma": 114}, {"hour": 36.92, "karma": 113}, {"hour": 37.92, "karma": 113}, {"hour": 38.92, "karma": 118}, {"hour": 39.92, "karma": 118}, {"hour": 40.92, "karma": 113}, {"hour": 41.92, "karma": 117}, {"hour": 42.92, "karma": 114}, {"hour": 43.92, "karma": 115}, {"hour": 44.92, "karma": 119}, {"hour": 45.92, "karma": 119}, {"hour": 46.92, "karma": 121}, {"hour": 47.92, "karma": 115}]}, {"mal_id": 54717, "progression": [{"hour": 0.98, "karma": 8}, {"hour": 1.3, "karma": 9}, {"hour": 1.98, "karma": 8}, {"hour": 2.98, "karma": 11}, {"hour": 3.98, "karma": 14}, {"hour": 4.98, "karma": 16}, {"hour": 5.98, "karma": 16}, {"hour": 6.67, "karma": 19}, {"hour": 6.75, "karma": 17}, {"hour": 6.81, "karma": 19}, {"hour": 6.98, "karma": 19}, {"hour": 7.31, "karma": 21}, {"hour": 7.98, "karma": 20}, {"hour": 8.98, "karma": 21}, {"hour": 9.98, "karma": 22}, {"hour": 10.98, "karma": 22}, {"hour": 12.98, "karma": 21}, {"hour": 13.98, "karma": 23}, {"hour": 14.98, "karma": 23}, {"hour": 15.98, "karma": 25}, {"hour": 16.98, "karma": 23}, {"hour": 17.01, "karma": 25}, {"hour": 17.98, "karma": 26}, {"hour": 18.98, "karma": 24}, {"hour": 19.98, "karma": 25}, {"hour": 20.98, "karma": 26}, {"hour": 21.98, "karma": 26}, {"hour": 22.98, "karma": 27}, {"hour": 23.98, "karma": 28}, {"hour": 24.98, "karma": 30}, {"hour": 25.98, "karma": 30}, {"hour": 26.98, "karma": 29}, {"hour": 27.98, "karma": 28}, {"hour": 28.98, "karma": 27}, {"hour": 29.98, "karma": 28}, {"hour": 30.98, "karma": 29}, {"hour": 31.98, "karma": 29}, {"hour": 32.98, "karma": 29}, {"hour": 33.98, "karma": 28}, {"hour": 34.98, "karma": 30}, {"hour": 35.98, "karma": 29}, {"hour": 36.98, "karma": 29}, {"hour": 37.98, "karma": 29}, {"hour": 38.98, "karma": 30}, {"hour": 39.98, "karma": 32}, {"hour": 40.98, "karma": 30}, {"hour": 41.98, "karma": 29}, {"hour": 42.98, "karma": 30}, {"hour": 43.98, "karma": 32}, {"hour": 44.98, "karma": 31}, {"hour": 45.98, "karma": 32}, {"hour": 46.98, "karma": 33}, {"hour": 47.98, "karma": 32}]}, {"mal_id": 55842, "progression": [{"hour": 2.72, "karma": 85}, {"hour": 3.04, "karma": 83}, {"hour": 3.72, "karma": 93}, {"hour": 4.72, "karma": 112}, {"hour": 5.72, "karma": 122}, {"hour": 6.72, "karma": 136}, {"hour": 7.72, "karma": 137}, {"hour": 8.42, "karma": 142}, {"hour": 8.5, "karma": 142}, {"hour": 8.56, "karma": 143}, {"hour": 8.72, "karma": 145}, {"hour": 9.05, "karma": 148}, {"hour": 9.72, "karma": 152}, {"hour": 10.72, "karma": 160}, {"hour": 11.72, "karma": 168}, {"hour": 12.72, "karma": 175}, {"hour": 14.72, "karma": 189}, {"hour": 15.72, "karma": 189}, {"hour": 16.72, "karma": 193}, {"hour": 17.72, "karma": 197}, {"hour": 18.72, "karma": 202}, {"hour": 18.75, "karma": 199}, {"hour": 19.72, "karma": 207}, {"hour": 20.72, "karma": 209}, {"hour": 21.72, "karma": 213}, {"hour": 22.72, "karma": 218}, {"hour": 23.72, "karma": 217}, {"hour": 24.72, "karma": 220}, {"hour": 25.72, "karma": 219}, {"hour": 26.72, "karma": 221}, {"hour": 27.72, "karma": 220}, {"hour": 28.72, "karma": 224}, {"hour": 29.72, "karma": 228}, {"hour": 30.72, "karma": 227}, {"hour": 31.72, "karma": 233}, {"hour": 32.72, "karma": 232}, {"hour": 33.72, "karma": 235}, {"hour": 34.72, "karma": 230}, {"hour": 35.72, "karma": 232}, {"hour": 36.72, "karma": 236}, {"hour": 37.72, "karma": 232}, {"hour": 38.72, "karma": 237}, {"hour": 39.72, "karma": 235}, {"hour": 40.72, "karma": 235}, {"hour": 41.72, "karma": 236}, {"hour": 42.72, "karma": 234}, {"hour": 43.72, "karma": 238}, {"hour": 44.72, "karma": 238}, {"hour": 45.72, "karma": 234}, {"hour": 46.72, "karma": 239}, {"hour": 47.72, "karma": 244}]}, {"mal_id": 59226, "progression": [{"hour": 2.92, "karma": 40}, {"hour": 3.24, "karma": 42}, {"hour": 3.92, "karma": 50}, {"hour": 4.92, "karma": 56}, {"hour": 5.92, "karma": 66}, {"hour": 6.92, "karma": 72}, {"hour": 7.92, "karma": 75}, {"hour": 8.62, "karma": 82}, {"hour": 8.7, "karma": 81}, {"hour": 8.76, "karma": 83}, {"hour": 8.92, "karma": 83}, {"hour": 9.25, "karma": 88}, {"hour": 9.92, "karma": 87}, {"hour": 10.92, "karma": 97}, {"hour": 11.92, "karma": 97}, {"hour": 12.92, "karma": 94}, {"hour": 14.92, "karma": 105}, {"hour": 15.92, "karma": 108}, {"hour": 16.92, "karma": 113}, {"hour": 17.92, "karma": 112}, {"hour": 18.92, "karma": 117}, {"hour": 18.95, "karma": 114}, {"hour": 19.92, "karma": 117}, {"hour": 20.92, "karma": 117}, {"hour": 21.92, "karma": 124}, {"hour": 22.92, "karma": 122}, {"hour": 23.92, "karma": 122}, {"hour": 24.92, "karma": 125}, {"hour": 25.92, "karma": 123}, {"hour": 26.92, "karma": 128}, {"hour": 27.92, "karma": 126}, {"hour": 28.92, "karma": 128}, {"hour": 29.92, "karma": 132}, {"hour": 30.92, "karma": 132}, {"hour": 31.92, "karma": 132}, {"hour": 32.92, "karma": 131}, {"hour": 33.92, "karma": 130}, {"hour": 34.92, "karma": 132}, {"hour": 35.92, "karma": 133}, {"hour": 36.92, "karma": 136}, {"hour": 37.92, "karma": 132}, {"hour": 38.92, "karma": 133}, {"hour": 39.92, "karma": 131}, {"hour": 40.92, "karma": 132}, {"hour": 41.92, "karma": 134}, {"hour": 42.92, "karma": 132}, {"hour": 43.92, "karma": 133}, {"hour": 44.92, "karma": 130}, {"hour": 45.92, "karma": 132}, {"hour": 46.92, "karma": 136}, {"hour": 47.92, "karma": 131}]}, {"mal_id": 58567, "progression": [{"hour": 3.38, "karma": 1621}, {"hour": 3.7, "karma": 1706}, {"hour": 4.38, "karma": 1833}, {"hour": 5.38, "karma": 2039}, {"hour": 6.38, "karma": 2231}, {"hour": 7.38, "karma": 2392}, {"hour": 8.38, "karma": 2518}, {"hour": 9.07, "karma": 2608}, {"hour": 9.15, "karma": 2622}, {"hour": 9.21, "karma": 2625}, {"hour": 9.38, "karma": 2638}, {"hour": 9.71, "karma": 2685}, {"hour": 10.38, "karma": 2755}, {"hour": 11.38, "karma": 2864}, {"hour": 12.38, "karma": 2943}, {"hour": 13.38, "karma": 3014}, {"hour": 15.38, "karma": 3123}, {"hour": 16.38, "karma": 3173}, {"hour": 17.38, "karma": 3214}, {"hour": 18.38, "karma": 3239}, {"hour": 19.38, "karma": 3273}, {"hour": 19.41, "karma": 3277}, {"hour": 20.38, "karma": 3290}, {"hour": 21.38, "karma": 3327}, {"hour": 22.38, "karma": 3356}, {"hour": 23.38, "karma": 3397}, {"hour": 24.38, "karma": 3425}, {"hour": 25.38, "karma": 3444}, {"hour": 26.38, "karma": 3476}, {"hour": 27.38, "karma": 3495}, {"hour": 28.38, "karma": 3518}, {"hour": 29.38, "karma": 3540}, {"hour": 30.38, "karma": 3554}, {"hour": 31.38, "karma": 3570}, {"hour": 32.38, "karma": 3584}, {"hour": 33.38, "karma": 3589}, {"hour": 34.38, "karma": 3611}, {"hour": 35.38, "karma": 3630}, {"hour": 36.38, "karma": 3635}, {"hour": 37.38, "karma": 3645}, {"hour": 38.38, "karma": 3654}, {"hour": 39.38, "karma": 3663}, {"hour": 40.38, "karma": 3669}, {"hour": 41.38, "karma": 3663}, {"hour": 42.38, "karma": 3670}, {"hour": 43.38, "karma": 3679}, {"hour": 44.38, "karma": 3679}, {"hour": 45.38, "karma": 3694}, {"hour": 46.38, "karma": 3692}, {"hour": 47.38, "karma": 3706}]}, {"mal_id": 55318, "progression": [{"hour": 3.92, "karma": 262}, {"hour": 4.24, "karma": 276}, {"hour": 4.92, "karma": 297}, {"hour": 5.92, "karma": 326}, {"hour": 6.92, "karma": 358}, {"hour": 7.92, "karma": 386}, {"hour": 8.92, "karma": 409}, {"hour": 9.62, "karma": 427}, {"hour": 9.7, "karma": 427}, {"hour": 9.76, "karma": 432}, {"hour": 9.92, "karma": 433}, {"hour": 10.25, "karma": 439}, {"hour": 10.92, "karma": 452}, {"hour": 11.92, "karma": 471}, {"hour": 12.92, "karma": 498}, {"hour": 13.92, "karma": 509}, {"hour": 15.92, "karma": 521}, {"hour": 16.92, "karma": 528}, {"hour": 17.92, "karma": 543}, {"hour": 18.92, "karma": 554}, {"hour": 19.92, "karma": 561}, {"hour": 19.96, "karma": 559}, {"hour": 20.92, "karma": 572}, {"hour": 21.92, "karma": 582}, {"hour": 22.92, "karma": 585}, {"hour": 23.92, "karma": 592}, {"hour": 24.92, "karma": 602}, {"hour": 25.92, "karma": 603}, {"hour": 26.92, "karma": 613}, {"hour": 27.92, "karma": 617}, {"hour": 28.92, "karma": 627}, {"hour": 29.92, "karma": 625}, {"hour": 30.92, "karma": 632}, {"hour": 31.92, "karma": 631}, {"hour": 32.92, "karma": 635}, {"hour": 33.92, "karma": 643}, {"hour": 34.92, "karma": 640}, {"hour": 35.92, "karma": 646}, {"hour": 36.92, "karma": 647}, {"hour": 37.92, "karma": 650}, {"hour": 38.92, "karma": 650}, {"hour": 39.92, "karma": 648}, {"hour": 40.92, "karma": 655}, {"hour": 41.92, "karma": 658}, {"hour": 42.92, "karma": 658}, {"hour": 43.92, "karma": 655}, {"hour": 44.92, "karma": 664}, {"hour": 45.92, "karma": 664}, {"hour": 46.92, "karma": 666}, {"hour": 47.92, "karma": 665}]}, {"mal_id": 56135, "progression": [{"hour": 3.97, "karma": 6}, {"hour": 4.29, "karma": 8}, {"hour": 4.97, "karma": 6}, {"hour": 5.97, "karma": 6}, {"hour": 6.97, "karma": 7}, {"hour": 7.97, "karma": 6}, {"hour": 8.97, "karma": 7}, {"hour": 9.67, "karma": 9}, {"hour": 9.75, "karma": 10}, {"hour": 9.81, "karma": 10}, {"hour": 9.97, "karma": 8}, {"hour": 10.3, "karma": 9}, {"hour": 10.97, "karma": 9}, {"hour": 11.97, "karma": 9}, {"hour": 12.97, "karma": 13}, {"hour": 13.97, "karma": 11}, {"hour": 15.97, "karma": 11}, {"hour": 16.97, "karma": 13}, {"hour": 17.97, "karma": 14}, {"hour": 18.97, "karma": 11}, {"hour": 19.97, "karma": 10}, {"hour": 20.01, "karma": 13}, {"hour": 20.97, "karma": 12}, {"hour": 21.97, "karma": 13}, {"hour": 22.97, "karma": 13}, {"hour": 23.97, "karma": 13}, {"hour": 24.97, "karma": 16}, {"hour": 25.97, "karma": 14}, {"hour": 26.97, "karma": 13}, {"hour": 27.97, "karma": 14}, {"hour": 28.97, "karma": 12}, {"hour": 29.97, "karma": 14}, {"hour": 30.97, "karma": 14}, {"hour": 31.97, "karma": 12}, {"hour": 32.97, "karma": 13}, {"hour": 33.97, "karma": 13}, {"hour": 34.97, "karma": 13}, {"hour": 35.97, "karma": 15}, {"hour": 36.97, "karma": 16}, {"hour": 37.97, "karma": 15}, {"hour": 38.97, "karma": 14}, {"hour": 39.97, "karma": 15}, {"hour": 40.97, "karma": 15}, {"hour": 41.97, "karma": 16}, {"hour": 42.97, "karma": 16}, {"hour": 43.97, "karma": 14}, {"hour": 44.97, "karma": 14}, {"hour": 45.97, "karma": 14}, {"hour": 46.97, "karma": 12}, {"hour": 47.97, "karma": 14}]}, {"mal_id": 58082, "progression": [{"hour": 4.42, "karma": 72}, {"hour": 4.74, "karma": 79}, {"hour": 5.42, "karma": 80}, {"hour": 6.42, "karma": 86}, {"hour": 7.42, "karma": 90}, {"hour": 8.42, "karma": 93}, {"hour": 9.42, "karma": 94}, {"hour": 10.12, "karma": 103}, {"hour": 10.2, "karma": 100}, {"hour": 10.26, "karma": 101}, {"hour": 10.42, "karma": 105}, {"hour": 10.75, "karma": 101}, {"hour": 11.42, "karma": 109}, {"hour": 12.42, "karma": 109}, {"hour": 13.42, "karma": 113}, {"hour": 14.42, "karma": 109}, {"hour": 16.42, "karma": 120}, {"hour": 17.42, "karma": 116}, {"hour": 18.42, "karma": 120}, {"hour": 19.42, "karma": 117}, {"hour": 20.42, "karma": 118}, {"hour": 20.45, "karma": 122}, {"hour": 21.42, "karma": 124}, {"hour": 22.42, "karma": 123}, {"hour": 23.42, "karma": 124}, {"hour": 24.42, "karma": 127}, {"hour": 25.42, "karma": 125}, {"hour": 26.42, "karma": 126}, {"hour": 27.42, "karma": 126}, {"hour": 28.42, "karma": 127}, {"hour": 29.42, "karma": 126}, {"hour": 30.42, "karma": 126}, {"hour": 31.42, "karma": 124}, {"hour": 32.42, "karma": 126}, {"hour": 33.42, "karma": 125}, {"hour": 34.42, "karma": 128}, {"hour": 35.42, "karma": 123}, {"hour": 36.42, "karma": 128}, {"hour": 37.42, "karma": 126}, {"hour": 38.42, "karma": 128}, {"hour": 39.42, "karma": 126}, {"hour": 40.42, "karma": 125}, {"hour": 41.42, "karma": 132}, {"hour": 42.42, "karma": 129}, {"hour": 43.42, "karma": 126}, {"hour": 44.42, "karma": 127}, {"hour": 45.42, "karma": 129}, {"hour": 46.42, "karma": 128}, {"hour": 47.42, "karma": 125}]}, {"mal_id": 59730, "progression": [{"hour": 4.42, "karma": 103}, {"hour": 4.74, "karma": 106}, {"hour": 5.42, "karma": 111}, {"hour": 6.42, "karma": 127}, {"hour": 7.42, "karma": 132}, {"hour": 8.42, "karma": 145}, {"hour": 9.42, "karma": 157}, {"hour": 10.12, "karma": 169}, {"hour": 10.2, "karma": 168}, {"hour": 10.26, "karma": 169}, {"hour": 10.42, "karma": 169}, {"hour": 10.75, "karma": 171}, {"hour": 11.42, "karma": 182}, {"hour": 12.42, "karma": 186}, {"hour": 13.42, "karma": 195}, {"hour": 14.42, "karma": 204}, {"hour": 16.42, "karma": 209}, {"hour": 17.42, "karma": 211}, {"hour": 18.42, "karma": 216}, {"hour": 19.42, "karma": 215}, {"hour": 20.42, "karma": 220}, {"hour": 20.46, "karma": 219}, {"hour": 21.42, "karma": 214}, {"hour": 22.42, "karma": 220}, {"hour": 23.42, "karma": 222}, {"hour": 24.42, "karma": 226}, {"hour": 25.42, "karma": 226}, {"hour": 26.42, "karma": 223}, {"hour": 27.42, "karma": 229}, {"hour": 28.42, "karma": 228}, {"hour": 29.42, "karma": 227}, {"hour": 30.42, "karma": 229}, {"hour": 31.42, "karma": 234}, {"hour": 32.42, "karma": 230}, {"hour": 33.42, "karma": 236}, {"hour": 34.42, "karma": 236}, {"hour": 35.42, "karma": 232}, {"hour": 36.42, "karma": 238}, {"hour": 37.42, "karma": 237}, {"hour": 38.42, "karma": 236}, {"hour": 39.42, "karma": 235}, {"hour": 40.42, "karma": 238}, {"hour": 41.42, "karma": 236}, {"hour": 42.42, "karma": 239}, {"hour": 43.42, "karma": 242}, {"hour": 44.42, "karma": 240}, {"hour": 45.42, "karma": 242}, {"hour": 46.42, "karma": 244}, {"hour": 47.42, "karma": 240}]}, {"mal_id": 58265, "progression": [{"hour": 5.32, "karma": 5}, {"hour": 5.64, "karma": 8}, {"hour": 6.32, "karma": 10}, {"hour": 7.32, "karma": 8}, {"hour": 8.32, "karma": 10}, {"hour": 9.32, "karma": 10}, {"hour": 10.32, "karma": 10}, {"hour": 11.02, "karma": 11}, {"hour": 11.1, "karma": 13}, {"hour": 11.16, "karma": 9}, {"hour": 11.32, "karma": 11}, {"hour": 11.65, "karma": 13}, {"hour": 12.32, "karma": 11}, {"hour": 13.32, "karma": 17}, {"hour": 14.32, "karma": 14}, {"hour": 15.32, "karma": 15}, {"hour": 17.32, "karma": 13}, {"hour": 18.32, "karma": 13}, {"hour": 19.32, "karma": 15}, {"hour": 20.32, "karma": 17}, {"hour": 21.32, "karma": 16}, {"hour": 21.36, "karma": 14}, {"hour": 22.32, "karma": 15}, {"hour": 23.32, "karma": 15}, {"hour": 24.32, "karma": 15}, {"hour": 25.32, "karma": 15}, {"hour": 26.32, "karma": 15}, {"hour": 27.32, "karma": 17}, {"hour": 28.32, "karma": 16}, {"hour": 29.32, "karma": 15}, {"hour": 30.32, "karma": 13}, {"hour": 31.32, "karma": 16}, {"hour": 32.32, "karma": 14}, {"hour": 33.32, "karma": 15}, {"hour": 34.32, "karma": 14}, {"hour": 35.32, "karma": 15}, {"hour": 36.32, "karma": 16}, {"hour": 37.32, "karma": 16}, {"hour": 38.32, "karma": 18}, {"hour": 39.32, "karma": 19}, {"hour": 40.32, "karma": 18}, {"hour": 41.32, "karma": 18}, {"hour": 42.32, "karma": 16}, {"hour": 43.32, "karma": 16}, {"hour": 44.32, "karma": 17}, {"hour": 45.32, "karma": 17}, {"hour": 46.32, "karma": 17}, {"hour": 47.32, "karma": 18}]}, {"mal_id": 52215, "progression": [{"hour": 5.42, "karma": 718}, {"hour": 5.74, "karma": 743}, {"hour": 6.42, "karma": 786}, {"hour": 7.42, "karma": 847}, {"hour": 8.42, "karma": 903}, {"hour": 9.42, "karma": 956}, {"hour": 10.42, "karma": 1013}, {"hour": 11.12, "karma": 1044}, {"hour": 11.2, "karma": 1049}, {"hour": 11.26, "karma": 1047}, {"hour": 11.42, "karma": 1060}, {"hour": 11.75, "karma": 1069}, {"hour": 12.42, "karma": 1087}, {"hour": 13.42, "karma": 1119}, {"hour": 14.42, "karma": 1152}, {"hour": 15.42, "karma": 1172}, {"hour": 17.42, "karma": 1207}, {"hour": 18.42, "karma": 1232}, {"hour": 19.42, "karma": 1247}, {"hour": 20.42, "karma": 1264}, {"hour": 21.42, "karma": 1285}, {"hour": 21.46, "karma": 1281}, {"hour": 22.42, "karma": 1297}, {"hour": 23.42, "karma": 1313}, {"hour": 24.42, "karma": 1328}, {"hour": 25.42, "karma": 1344}, {"hour": 26.42, "karma": 1353}, {"hour": 27.42, "karma": 1361}, {"hour": 28.42, "karma": 1369}, {"hour": 29.42, "karma": 1379}, {"hour": 30.42, "karma": 1393}, {"hour": 31.42, "karma": 1396}, {"hour": 32.42, "karma": 1396}, {"hour": 33.42, "karma": 1409}, {"hour": 34.42, "karma": 1413}, {"hour": 35.42, "karma": 1423}, {"hour": 36.42, "karma": 1429}, {"hour": 37.42, "karma": 1437}, {"hour": 38.42, "karma": 1442}, {"hour": 39.42, "karma": 1445}, {"hour": 40.42, "karma": 1452}, {"hour": 41.42, "karma": 1449}, {"hour": 42.42, "karma": 1453}, {"hour": 43.42, "karma": 1457}, {"hour": 44.42, "karma": 1460}, {"hour": 45.42, "karma": 1467}, {"hour": 46.42, "karma": 1467}, {"hour": 47.42, "karma": 1462}]}, {"mal_id": 60407, "progression": [{"hour": 0.42, "karma": 2}, {"hour": 1.11, "karma": 5}, {"hour": 1.19, "karma": 5}, {"hour": 1.25, "karma": 5}, {"hour": 1.42, "karma": 8}, {"hour": 1.75, "karma": 8}, {"hour": 2.42, "karma": 6}, {"hour": 3.42, "karma": 9}, {"hour": 4.42, "karma": 12}, {"hour": 5.42, "karma": 13}, {"hour": 7.42, "karma": 18}, {"hour": 8.42, "karma": 21}, {"hour": 9.42, "karma": 20}, {"hour": 10.42, "karma": 26}, {"hour": 11.42, "karma": 23}, {"hour": 11.45, "karma": 25}, {"hour": 12.42, "karma": 26}, {"hour": 13.42, "karma": 27}, {"hour": 14.42, "karma": 26}, {"hour": 15.42, "karma": 27}, {"hour": 16.42, "karma": 26}, {"hour": 17.42, "karma": 29}, {"hour": 18.42, "karma": 28}, {"hour": 19.42, "karma": 28}, {"hour": 20.42, "karma": 33}, {"hour": 21.42, "karma": 32}, {"hour": 22.42, "karma": 29}, {"hour": 23.42, "karma": 30}, {"hour": 24.42, "karma": 35}, {"hour": 25.42, "karma": 34}, {"hour": 26.42, "karma": 33}, {"hour": 27.42, "karma": 37}, {"hour": 28.42, "karma": 34}, {"hour": 29.42, "karma": 35}, {"hour": 30.42, "karma": 32}, {"hour": 31.42, "karma": 36}, {"hour": 32.42, "karma": 37}, {"hour": 33.42, "karma": 38}, {"hour": 34.42, "karma": 36}, {"hour": 35.42, "karma": 34}, {"hour": 36.42, "karma": 40}, {"hour": 37.42, "karma": 33}, {"hour": 38.42, "karma": 34}, {"hour": 39.42, "karma": 37}, {"hour": 40.42, "karma": 37}, {"hour": 41.42, "karma": 39}, {"hour": 42.42, "karma": 34}, {"hour": 43.42, "karma": 35}, {"hour": 44.42, "karma": 37}, {"hour": 45.42, "karma": 34}, {"hour": 46.42, "karma": 36}, {"hour": 47.42, "karma": 36}]}, {"mal_id": 58572, "progression": [{"hour": 0.92, "karma": 43}, {"hour": 1.92, "karma": 112}, {"hour": 2.92, "karma": 186}, {"hour": 3.92, "karma": 275}, {"hour": 3.95, "karma": 278}, {"hour": 4.92, "karma": 376}, {"hour": 5.92, "karma": 475}, {"hour": 6.92, "karma": 540}, {"hour": 7.92, "karma": 621}, {"hour": 8.92, "karma": 686}, {"hour": 9.92, "karma": 745}, {"hour": 10.92, "karma": 816}, {"hour": 11.92, "karma": 857}, {"hour": 12.92, "karma": 920}, {"hour": 13.92, "karma": 973}, {"hour": 14.92, "karma": 1010}, {"hour": 15.92, "karma": 1060}, {"hour": 16.92, "karma": 1078}, {"hour": 17.92, "karma": 1107}, {"hour": 18.92, "karma": 1132}, {"hour": 19.92, "karma": 1145}, {"hour": 20.92, "karma": 1174}, {"hour": 21.92, "karma": 1183}, {"hour": 22.92, "karma": 1190}, {"hour": 23.92, "karma": 1206}, {"hour": 24.92, "karma": 1209}, {"hour": 25.92, "karma": 1215}, {"hour": 26.92, "karma": 1218}, {"hour": 27.92, "karma": 1235}, {"hour": 28.92, "karma": 1250}, {"hour": 29.92, "karma": 1245}, {"hour": 30.92, "karma": 1258}, {"hour": 31.92, "karma": 1262}, {"hour": 32.92, "karma": 1275}, {"hour": 33.92, "karma": 1282}, {"hour": 34.92, "karma": 1290}, {"hour": 35.92, "karma": 1298}, {"hour": 36.92, "karma": 1305}, {"hour": 37.92, "karma": 1316}, {"hour": 38.92, "karma": 1322}, {"hour": 39.92, "karma": 1320}, {"hour": 40.92, "karma": 1322}, {"hour": 41.92, "karma": 1326}, {"hour": 42.92, "karma": 1326}, {"hour": 43.92, "karma": 1331}, {"hour": 44.92, "karma": 1331}, {"hour": 45.92, "karma": 1342}, {"hour": 46.92, "karma": 1338}, {"hour": 47.92, "karma": 1336}]}, {"mal_id": 53924, "progression": [{"hour": 0.92, "karma": 3}, {"hour": 1.92, "karma": 12}, {"hour": 2.92, "karma": 24}, {"hour": 2.95, "karma": 24}, {"hour": 3.92, "karma": 34}, {"hour": 4.92, "karma": 49}, {"hour": 5.92, "karma": 59}, {"hour": 6.92, "karma": 71}, {"hour": 7.92, "karma": 84}, {"hour": 8.92, "karma": 95}, {"hour": 9.92, "karma": 105}, {"hour": 10.92, "karma": 107}, {"hour": 11.92, "karma": 120}, {"hour": 12.92, "karma": 128}, {"hour": 13.92, "karma": 133}, {"hour": 14.92, "karma": 138}, {"hour": 15.92, "karma": 145}, {"hour": 16.92, "karma": 145}, {"hour": 17.92, "karma": 150}, {"hour": 18.92, "karma": 149}, {"hour": 19.92, "karma": 157}, {"hour": 20.92, "karma": 160}, {"hour": 21.92, "karma": 157}, {"hour": 22.92, "karma": 166}, {"hour": 23.92, "karma": 166}, {"hour": 24.92, "karma": 166}, {"hour": 25.92, "karma": 162}, {"hour": 26.92, "karma": 161}, {"hour": 27.92, "karma": 165}, {"hour": 28.92, "karma": 171}, {"hour": 29.92, "karma": 169}, {"hour": 30.92, "karma": 166}, {"hour": 31.92, "karma": 171}, {"hour": 32.92, "karma": 168}, {"hour": 33.92, "karma": 174}, {"hour": 34.92, "karma": 171}, {"hour": 35.92, "karma": 172}, {"hour": 36.92, "karma": 175}, {"hour": 37.92, "karma": 175}, {"hour": 38.92, "karma": 175}, {"hour": 39.92, "karma": 177}, {"hour": 40.92, "karma": 180}, {"hour": 41.92, "karma": 179}, {"hour": 42.92, "karma": 183}, {"hour": 43.92, "karma": 181}, {"hour": 44.92, "karma": 178}, {"hour": 45.92, "karma": 182}, {"hour": 46.92, "karma": 182}, {"hour": 47.92, "karma": 186}]}, {"mal_id": 57050, "progression": [{"hour": 0.72, "karma": 1}, {"hour": 1.72, "karma": 3}, {"hour": 2.72, "karma": 2}, {"hour": 3.72, "karma": 0}, {"hour": 4.72, "karma": 4}, {"hour": 5.72, "karma": 2}, {"hour": 6.72, "karma": 2}, {"hour": 7.72, "karma": 0}, {"hour": 8.72, "karma": 1}, {"hour": 9.72, "karma": 2}, {"hour": 10.72, "karma": 3}, {"hour": 11.72, "karma": 2}, {"hour": 12.72, "karma": 2}, {"hour": 13.72, "karma": 4}, {"hour": 14.72, "karma": 3}, {"hour": 15.72, "karma": 5}, {"hour": 16.72, "karma": 6}, {"hour": 17.72, "karma": 4}, {"hour": 18.72, "karma": 3}, {"hour": 19.72, "karma": 4}, {"hour": 20.72, "karma": 7}, {"hour": 21.72, "karma": 4}, {"hour": 22.72, "karma": 6}, {"hour": 23.72, "karma": 6}, {"hour": 24.72, "karma": 6}, {"hour": 25.72, "karma": 6}, {"hour": 26.72, "karma": 5}, {"hour": 27.72, "karma": 5}, {"hour": 28.72, "karma": 4}, {"hour": 29.72, "karma": 6}, {"hour": 30.72, "karma": 7}, {"hour": 31.72, "karma": 7}, {"hour": 32.72, "karma": 5}, {"hour": 33.72, "karma": 3}, {"hour": 34.72, "karma": 4}, {"hour": 35.72, "karma": 4}, {"hour": 36.72, "karma": 6}, {"hour": 37.72, "karma": 6}, {"hour": 38.72, "karma": 6}, {"hour": 39.72, "karma": 7}, {"hour": 40.72, "karma": 4}, {"hour": 41.72, "karma": 7}, {"hour": 42.72, "karma": 7}, {"hour": 43.72, "karma": 6}, {"hour": 44.72, "karma": 7}, {"hour": 45.72, "karma": 6}, {"hour": 46.72, "karma": 7}, {"hour": 47.72, "karma": 9}]}, {"mal_id": 57616, "progression": [{"hour": 0.92, "karma": 188}, {"hour": 1.92, "karma": 338}, {"hour": 2.92, "karma": 469}, {"hour": 3.92, "karma": 590}, {"hour": 4.92, "karma": 695}, {"hour": 5.92, "karma": 799}, {"hour": 6.92, "karma": 881}, {"hour": 7.92, "karma": 964}, {"hour": 8.92, "karma": 1029}, {"hour": 9.92, "karma": 1081}, {"hour": 10.92, "karma": 1133}, {"hour": 11.92, "karma": 1171}, {"hour": 12.92, "karma": 1202}, {"hour": 13.92, "karma": 1245}, {"hour": 14.92, "karma": 1276}, {"hour": 15.92, "karma": 1297}, {"hour": 16.92, "karma": 1320}, {"hour": 17.92, "karma": 1348}, {"hour": 18.92, "karma": 1360}, {"hour": 19.92, "karma": 1376}, {"hour": 20.92, "karma": 1382}, {"hour": 21.92, "karma": 1390}, {"hour": 22.92, "karma": 1397}, {"hour": 23.92, "karma": 1414}, {"hour": 24.92, "karma": 1430}, {"hour": 25.92, "karma": 1435}, {"hour": 26.92, "karma": 1451}, {"hour": 27.92, "karma": 1460}, {"hour": 28.92, "karma": 1477}, {"hour": 29.92, "karma": 1475}, {"hour": 30.92, "karma": 1484}, {"hour": 31.92, "karma": 1484}, {"hour": 32.92, "karma": 1498}, {"hour": 33.92, "karma": 1498}, {"hour": 34.92, "karma": 1499}, {"hour": 35.92, "karma": 1505}, {"hour": 36.92, "karma": 1507}, {"hour": 37.92, "karma": 1508}, {"hour": 38.92, "karma": 1511}, {"hour": 39.92, "karma": 1509}, {"hour": 40.92, "karma": 1521}, {"hour": 41.92, "karma": 1519}, {"hour": 42.92, "karma": 1522}, {"hour": 43.92, "karma": 1523}, {"hour": 44.92, "karma": 1528}, {"hour": 45.92, "karma": 1527}, {"hour": 46.92, "karma": 1533}, {"hour": 47.92, "karma": 1534}]}, {"mal_id": 59514, "progression": [{"hour": 0.91, "karma": 28}, {"hour": 1.92, "karma": 73}, {"hour": 2.91, "karma": 125}, {"hour": 3.91, "karma": 147}, {"hour": 4.91, "karma": 177}, {"hour": 5.91, "karma": 193}, {"hour": 6.92, "karma": 224}, {"hour": 7.91, "karma": 240}, {"hour": 8.92, "karma": 254}, {"hour": 9.91, "karma": 276}, {"hour": 10.91, "karma": 288}, {"hour": 11.91, "karma": 296}, {"hour": 12.91, "karma": 305}, {"hour": 13.92, "karma": 327}, {"hour": 14.91, "karma": 334}, {"hour": 15.92, "karma": 340}, {"hour": 16.92, "karma": 346}, {"hour": 17.91, "karma": 351}, {"hour": 18.91, "karma": 356}, {"hour": 19.91, "karma": 355}, {"hour": 20.91, "karma": 360}, {"hour": 21.91, "karma": 364}, {"hour": 22.91, "karma": 366}, {"hour": 23.91, "karma": 365}, {"hour": 24.91, "karma": 368}, {"hour": 25.92, "karma": 377}, {"hour": 26.91, "karma": 378}, {"hour": 27.91, "karma": 384}, {"hour": 28.91, "karma": 378}, {"hour": 29.91, "karma": 379}, {"hour": 30.91, "karma": 384}, {"hour": 31.92, "karma": 383}, {"hour": 32.91, "karma": 383}, {"hour": 33.92, "karma": 382}, {"hour": 34.91, "karma": 386}, {"hour": 35.91, "karma": 388}, {"hour": 36.91, "karma": 385}, {"hour": 37.92, "karma": 385}, {"hour": 38.91, "karma": 384}, {"hour": 39.92, "karma": 382}, {"hour": 40.91, "karma": 384}, {"hour": 41.92, "karma": 387}, {"hour": 42.91, "karma": 388}, {"hour": 43.91, "karma": 394}, {"hour": 44.91, "karma": 394}, {"hour": 45.91, "karma": 395}, {"hour": 46.91, "karma": 391}, {"hour": 47.91, "karma": 399}]}, {"mal_id": 58502, "progression": [{"hour": 0.72, "karma": 69}, {"hour": 1.72, "karma": 181}, {"hour": 2.72, "karma": 269}, {"hour": 3.72, "karma": 349}, {"hour": 4.72, "karma": 405}, {"hour": 5.72, "karma": 456}, {"hour": 6.72, "karma": 511}, {"hour": 7.72, "karma": 557}, {"hour": 8.72, "karma": 589}, {"hour": 9.72, "karma": 633}, {"hour": 10.72, "karma": 657}, {"hour": 11.72, "karma": 691}, {"hour": 12.72, "karma": 723}, {"hour": 13.72, "karma": 744}, {"hour": 14.72, "karma": 758}, {"hour": 15.72, "karma": 771}, {"hour": 16.72, "karma": 774}, {"hour": 17.72, "karma": 792}, {"hour": 18.72, "karma": 804}, {"hour": 19.72, "karma": 811}, {"hour": 20.72, "karma": 825}, {"hour": 21.72, "karma": 832}, {"hour": 22.72, "karma": 848}, {"hour": 23.72, "karma": 849}, {"hour": 24.72, "karma": 862}, {"hour": 25.72, "karma": 873}, {"hour": 26.72, "karma": 877}, {"hour": 27.72, "karma": 882}, {"hour": 28.72, "karma": 893}, {"hour": 29.72, "karma": 904}, {"hour": 30.72, "karma": 914}, {"hour": 31.72, "karma": 915}, {"hour": 32.72, "karma": 922}, {"hour": 33.72, "karma": 919}, {"hour": 34.72, "karma": 926}, {"hour": 35.72, "karma": 928}, {"hour": 36.72, "karma": 935}, {"hour": 37.72, "karma": 932}, {"hour": 38.72, "karma": 937}, {"hour": 39.72, "karma": 939}, {"hour": 40.72, "karma": 937}, {"hour": 41.72, "karma": 947}, {"hour": 42.72, "karma": 947}, {"hour": 43.72, "karma": 950}, {"hour": 44.72, "karma": 947}, {"hour": 45.72, "karma": 945}, {"hour": 46.72, "karma": 955}, {"hour": 47.72, "karma": 953}]}, {"mal_id": 60410, "progression": [{"hour": 0.22, "karma": 1}, {"hour": 1.22, "karma": 3}, {"hour": 2.22, "karma": 3}, {"hour": 3.22, "karma": 3}, {"hour": 4.22, "karma": 3}, {"hour": 5.22, "karma": 3}, {"hour": 6.22, "karma": 3}, {"hour": 7.22, "karma": 3}, {"hour": 8.22, "karma": 3}, {"hour": 9.22, "karma": 3}, {"hour": 10.22, "karma": 3}, {"hour": 11.22, "karma": 4}, {"hour": 12.22, "karma": 3}, {"hour": 13.22, "karma": 4}, {"hour": 14.22, "karma": 3}, {"hour": 15.22, "karma": 4}, {"hour": 16.22, "karma": 4}, {"hour": 17.22, "karma": 2}, {"hour": 18.22, "karma": 4}, {"hour": 19.22, "karma": 4}, {"hour": 20.22, "karma": 5}, {"hour": 21.22, "karma": 3}, {"hour": 22.22, "karma": 2}, {"hour": 23.22, "karma": 3}, {"hour": 24.22, "karma": 3}, {"hour": 25.22, "karma": 2}, {"hour": 26.22, "karma": 2}, {"hour": 27.22, "karma": 3}, {"hour": 28.22, "karma": 5}, {"hour": 29.22, "karma": 4}, {"hour": 30.22, "karma": 2}, {"hour": 31.22, "karma": 3}, {"hour": 32.22, "karma": 3}, {"hour": 33.22, "karma": 3}, {"hour": 34.22, "karma": 4}, {"hour": 35.22, "karma": 5}, {"hour": 36.22, "karma": 4}, {"hour": 37.22, "karma": 3}, {"hour": 38.22, "karma": 1}, {"hour": 39.22, "karma": 4}, {"hour": 40.22, "karma": 1}, {"hour": 41.22, "karma": 5}, {"hour": 42.22, "karma": 3}, {"hour": 43.22, "karma": 3}, {"hour": 44.22, "karma": 4}, {"hour": 45.22, "karma": 3}, {"hour": 46.22, "karma": 4}, {"hour": 47.22, "karma": 3}]}, {"mal_id": 56701, "progression": [{"hour": 0.38, "karma": 8}, {"hour": 1.38, "karma": 36}, {"hour": 2.38, "karma": 60}, {"hour": 3.38, "karma": 83}, {"hour": 4.38, "karma": 108}, {"hour": 5.38, "karma": 125}, {"hour": 6.38, "karma": 136}, {"hour": 7.38, "karma": 147}, {"hour": 8.38, "karma": 164}, {"hour": 9.38, "karma": 187}, {"hour": 10.38, "karma": 185}, {"hour": 11.38, "karma": 195}, {"hour": 12.38, "karma": 204}, {"hour": 13.38, "karma": 220}, {"hour": 14.38, "karma": 227}, {"hour": 15.38, "karma": 229}, {"hour": 16.38, "karma": 239}, {"hour": 17.38, "karma": 242}, {"hour": 18.38, "karma": 246}, {"hour": 19.38, "karma": 250}, {"hour": 20.38, "karma": 252}, {"hour": 21.38, "karma": 254}, {"hour": 22.38, "karma": 259}, {"hour": 23.38, "karma": 265}, {"hour": 24.38, "karma": 266}, {"hour": 25.38, "karma": 271}, {"hour": 26.38, "karma": 271}, {"hour": 27.38, "karma": 279}, {"hour": 28.38, "karma": 283}, {"hour": 29.38, "karma": 288}, {"hour": 30.38, "karma": 286}, {"hour": 31.38, "karma": 291}, {"hour": 31.71, "karma": 297}, {"hour": 31.87, "karma": 294}, {"hour": 32.38, "karma": 293}, {"hour": 33.38, "karma": 293}, {"hour": 34.38, "karma": 296}, {"hour": 35.38, "karma": 298}, {"hour": 36.38, "karma": 301}, {"hour": 37.38, "karma": 298}, {"hour": 38.38, "karma": 298}, {"hour": 39.38, "karma": 303}, {"hour": 40.38, "karma": 304}, {"hour": 41.38, "karma": 301}, {"hour": 42.38, "karma": 300}, {"hour": 43.38, "karma": 306}, {"hour": 44.38, "karma": 304}, {"hour": 45.38, "karma": 306}, {"hour": 46.38, "karma": 303}, {"hour": 47.38, "karma": 303}]}, {"mal_id": 59349, "progression": [{"hour": 0.38, "karma": 8}, {"hour": 1.38, "karma": 18}, {"hour": 2.38, "karma": 36}, {"hour": 3.38, "karma": 54}, {"hour": 4.38, "karma": 69}, {"hour": 5.38, "karma": 83}, {"hour": 6.38, "karma": 93}, {"hour": 7.38, "karma": 115}, {"hour": 8.38, "karma": 124}, {"hour": 9.38, "karma": 138}, {"hour": 10.38, "karma": 152}, {"hour": 11.38, "karma": 151}, {"hour": 12.38, "karma": 163}, {"hour": 13.38, "karma": 170}, {"hour": 14.38, "karma": 184}, {"hour": 15.38, "karma": 186}, {"hour": 16.38, "karma": 195}, {"hour": 17.38, "karma": 192}, {"hour": 18.38, "karma": 193}, {"hour": 19.38, "karma": 195}, {"hour": 20.38, "karma": 196}, {"hour": 21.38, "karma": 199}, {"hour": 22.38, "karma": 204}, {"hour": 23.38, "karma": 211}, {"hour": 24.38, "karma": 209}, {"hour": 25.38, "karma": 212}, {"hour": 26.38, "karma": 215}, {"hour": 27.38, "karma": 218}, {"hour": 28.38, "karma": 217}, {"hour": 29.38, "karma": 222}, {"hour": 30.38, "karma": 225}, {"hour": 30.71, "karma": 226}, {"hour": 30.87, "karma": 225}, {"hour": 31.38, "karma": 226}, {"hour": 32.38, "karma": 225}, {"hour": 33.38, "karma": 223}, {"hour": 34.38, "karma": 228}, {"hour": 35.38, "karma": 226}, {"hour": 36.38, "karma": 227}, {"hour": 37.38, "karma": 224}, {"hour": 38.38, "karma": 230}, {"hour": 39.38, "karma": 226}, {"hour": 40.38, "karma": 230}, {"hour": 41.38, "karma": 232}, {"hour": 42.38, "karma": 229}, {"hour": 43.38, "karma": 231}, {"hour": 44.38, "karma": 228}, {"hour": 45.38, "karma": 234}, {"hour": 46.38, "karma": 231}, {"hour": 47.38, "karma": 234}]}, {"mal_id": 57152, "progression": [{"hour": 0.48, "karma": 2}, {"hour": 1.48, "karma": 2}, {"hour": 2.48, "karma": 3}, {"hour": 3.48, "karma": 4}, {"hour": 4.48, "karma": 7}, {"hour": 5.48, "karma": 3}, {"hour": 6.48, "karma": 9}, {"hour": 7.48, "karma": 5}, {"hour": 8.48, "karma": 6}, {"hour": 9.48, "karma": 9}, {"hour": 10.48, "karma": 8}, {"hour": 11.48, "karma": 9}, {"hour": 12.48, "karma": 11}, {"hour": 13.48, "karma": 15}, {"hour": 14.48, "karma": 13}, {"hour": 15.48, "karma": 13}, {"hour": 16.48, "karma": 13}, {"hour": 17.48, "karma": 12}, {"hour": 18.48, "karma": 15}, {"hour": 19.48, "karma": 14}, {"hour": 20.48, "karma": 12}, {"hour": 21.48, "karma": 14}, {"hour": 22.48, "karma": 11}, {"hour": 23.48, "karma": 13}, {"hour": 24.48, "karma": 13}, {"hour": 25.48, "karma": 14}, {"hour": 26.48, "karma": 13}, {"hour": 27.48, "karma": 14}, {"hour": 28.48, "karma": 13}, {"hour": 29.48, "karma": 14}, {"hour": 30.48, "karma": 15}, {"hour": 30.81, "karma": 14}, {"hour": 30.97, "karma": 12}, {"hour": 31.48, "karma": 14}, {"hour": 32.48, "karma": 14}, {"hour": 33.48, "karma": 12}, {"hour": 34.48, "karma": 13}, {"hour": 35.48, "karma": 12}, {"hour": 36.48, "karma": 14}, {"hour": 37.48, "karma": 13}, {"hour": 38.48, "karma": 13}, {"hour": 39.48, "karma": 13}, {"hour": 40.48, "karma": 14}, {"hour": 41.48, "karma": 11}, {"hour": 42.48, "karma": 13}, {"hour": 43.48, "karma": 13}, {"hour": 44.48, "karma": 12}, {"hour": 45.48, "karma": 13}, {"hour": 46.48, "karma": 13}, {"hour": 47.48, "karma": 14}]}, {"mal_id": 59361, "progression": [{"hour": 0.88, "karma": 32}, {"hour": 1.88, "karma": 62}, {"hour": 2.88, "karma": 90}, {"hour": 3.88, "karma": 112}, {"hour": 4.88, "karma": 148}, {"hour": 5.88, "karma": 189}, {"hour": 6.88, "karma": 215}, {"hour": 7.88, "karma": 241}, {"hour": 8.88, "karma": 258}, {"hour": 9.88, "karma": 279}, {"hour": 10.88, "karma": 301}, {"hour": 11.88, "karma": 318}, {"hour": 12.88, "karma": 329}, {"hour": 13.88, "karma": 344}, {"hour": 14.88, "karma": 359}, {"hour": 15.88, "karma": 366}, {"hour": 16.88, "karma": 377}, {"hour": 17.88, "karma": 383}, {"hour": 18.88, "karma": 382}, {"hour": 19.88, "karma": 389}, {"hour": 20.88, "karma": 403}, {"hour": 21.88, "karma": 406}, {"hour": 22.88, "karma": 418}, {"hour": 23.88, "karma": 418}, {"hour": 24.88, "karma": 424}, {"hour": 25.88, "karma": 427}, {"hour": 26.88, "karma": 431}, {"hour": 27.88, "karma": 439}, {"hour": 28.88, "karma": 436}, {"hour": 29.88, "karma": 439}, {"hour": 30.88, "karma": 446}, {"hour": 31.21, "karma": 447}, {"hour": 31.37, "karma": 441}, {"hour": 31.88, "karma": 443}, {"hour": 32.88, "karma": 448}, {"hour": 33.88, "karma": 453}, {"hour": 34.88, "karma": 453}, {"hour": 35.88, "karma": 456}, {"hour": 36.88, "karma": 458}, {"hour": 37.88, "karma": 453}, {"hour": 38.88, "karma": 465}, {"hour": 39.88, "karma": 462}, {"hour": 40.88, "karma": 457}, {"hour": 41.88, "karma": 462}, {"hour": 42.88, "karma": 462}, {"hour": 43.88, "karma": 466}, {"hour": 44.88, "karma": 465}, {"hour": 45.88, "karma": 467}, {"hour": 46.88, "karma": 464}, {"hour": 47.88, "karma": 465}]}, {"mal_id": 58853, "progression": [{"hour": 0.92, "karma": 5}, {"hour": 1.92, "karma": 20}, {"hour": 2.92, "karma": 29}, {"hour": 3.92, "karma": 37}, {"hour": 4.92, "karma": 46}, {"hour": 5.92, "karma": 55}, {"hour": 6.92, "karma": 63}, {"hour": 7.92, "karma": 74}, {"hour": 8.92, "karma": 77}, {"hour": 9.92, "karma": 82}, {"hour": 10.92, "karma": 94}, {"hour": 11.92, "karma": 98}, {"hour": 12.92, "karma": 96}, {"hour": 13.92, "karma": 102}, {"hour": 14.92, "karma": 105}, {"hour": 15.92, "karma": 99}, {"hour": 16.92, "karma": 105}, {"hour": 17.92, "karma": 105}, {"hour": 18.92, "karma": 106}, {"hour": 19.92, "karma": 102}, {"hour": 20.92, "karma": 105}, {"hour": 21.92, "karma": 110}, {"hour": 22.92, "karma": 109}, {"hour": 23.92, "karma": 109}, {"hour": 24.92, "karma": 112}, {"hour": 25.92, "karma": 113}, {"hour": 26.92, "karma": 113}, {"hour": 27.92, "karma": 111}, {"hour": 28.92, "karma": 114}, {"hour": 29.26, "karma": 115}, {"hour": 29.41, "karma": 113}, {"hour": 29.92, "karma": 117}, {"hour": 30.92, "karma": 115}, {"hour": 31.92, "karma": 119}, {"hour": 32.92, "karma": 116}, {"hour": 33.92, "karma": 116}, {"hour": 34.92, "karma": 117}, {"hour": 35.92, "karma": 117}, {"hour": 36.92, "karma": 113}, {"hour": 37.92, "karma": 116}, {"hour": 38.92, "karma": 120}, {"hour": 39.92, "karma": 117}, {"hour": 40.92, "karma": 115}, {"hour": 41.92, "karma": 118}, {"hour": 42.92, "karma": 119}, {"hour": 43.92, "karma": 113}, {"hour": 44.92, "karma": 116}, {"hour": 45.92, "karma": 116}, {"hour": 46.92, "karma": 120}, {"hour": 47.92, "karma": 118}]}, {"mal_id": 58437, "progression": [{"hour": 0.72, "karma": 6}, {"hour": 1.72, "karma": 9}, {"hour": 2.72, "karma": 15}, {"hour": 3.72, "karma": 20}, {"hour": 4.72, "karma": 27}, {"hour": 5.72, "karma": 34}, {"hour": 6.72, "karma": 36}, {"hour": 7.72, "karma": 36}, {"hour": 8.72, "karma": 41}, {"hour": 9.72, "karma": 42}, {"hour": 10.72, "karma": 44}, {"hour": 11.72, "karma": 48}, {"hour": 12.72, "karma": 51}, {"hour": 13.72, "karma": 53}, {"hour": 14.72, "karma": 52}, {"hour": 15.72, "karma": 55}, {"hour": 16.72, "karma": 62}, {"hour": 17.72, "karma": 53}, {"hour": 18.72, "karma": 59}, {"hour": 19.72, "karma": 59}, {"hour": 20.72, "karma": 59}, {"hour": 21.72, "karma": 61}, {"hour": 22.72, "karma": 63}, {"hour": 23.72, "karma": 66}, {"hour": 24.72, "karma": 65}, {"hour": 25.72, "karma": 68}, {"hour": 26.72, "karma": 68}, {"hour": 27.72, "karma": 68}, {"hour": 28.05, "karma": 74}, {"hour": 28.21, "karma": 74}, {"hour": 28.72, "karma": 69}, {"hour": 29.72, "karma": 71}, {"hour": 30.72, "karma": 74}, {"hour": 31.72, "karma": 70}, {"hour": 32.72, "karma": 75}, {"hour": 33.72, "karma": 74}, {"hour": 34.72, "karma": 76}, {"hour": 35.72, "karma": 76}, {"hour": 36.72, "karma": 70}, {"hour": 37.72, "karma": 72}, {"hour": 38.72, "karma": 73}, {"hour": 39.72, "karma": 73}, {"hour": 40.72, "karma": 75}, {"hour": 41.72, "karma": 71}, {"hour": 42.72, "karma": 73}, {"hour": 43.72, "karma": 74}, {"hour": 44.72, "karma": 76}, {"hour": 45.72, "karma": 74}, {"hour": 46.72, "karma": 73}, {"hour": 47.72, "karma": 76}]}, {"mal_id": 57533, "progression": [{"hour": 0.87, "karma": 6}, {"hour": 1.87, "karma": 11}, {"hour": 2.87, "karma": 17}, {"hour": 3.87, "karma": 18}, {"hour": 4.87, "karma": 20}, {"hour": 5.87, "karma": 23}, {"hour": 6.87, "karma": 26}, {"hour": 7.2, "karma": 26}, {"hour": 7.36, "karma": 29}, {"hour": 7.87, "karma": 33}, {"hour": 8.87, "karma": 36}, {"hour": 9.87, "karma": 34}, {"hour": 10.87, "karma": 37}, {"hour": 11.87, "karma": 40}, {"hour": 12.87, "karma": 40}, {"hour": 13.87, "karma": 41}, {"hour": 14.87, "karma": 40}, {"hour": 15.87, "karma": 38}, {"hour": 16.87, "karma": 40}, {"hour": 17.87, "karma": 40}, {"hour": 18.87, "karma": 38}, {"hour": 19.87, "karma": 39}, {"hour": 20.87, "karma": 40}, {"hour": 21.87, "karma": 37}, {"hour": 22.87, "karma": 41}, {"hour": 23.87, "karma": 46}, {"hour": 24.87, "karma": 44}, {"hour": 25.87, "karma": 45}, {"hour": 26.87, "karma": 44}, {"hour": 27.87, "karma": 48}, {"hour": 28.87, "karma": 44}, {"hour": 29.87, "karma": 47}, {"hour": 30.87, "karma": 42}, {"hour": 31.87, "karma": 43}, {"hour": 32.87, "karma": 41}, {"hour": 33.87, "karma": 46}, {"hour": 34.87, "karma": 46}, {"hour": 35.87, "karma": 44}, {"hour": 36.87, "karma": 43}, {"hour": 37.87, "karma": 45}, {"hour": 38.87, "karma": 45}, {"hour": 39.87, "karma": 48}, {"hour": 40.87, "karma": 45}, {"hour": 41.87, "karma": 49}, {"hour": 42.87, "karma": 44}, {"hour": 43.87, "karma": 44}, {"hour": 44.87, "karma": 46}, {"hour": 45.87, "karma": 49}, {"hour": 46.87, "karma": 47}, {"hour": 47.87, "karma": 47}]}, {"mal_id": 59002, "progression": [{"hour": 0.67, "karma": 6}, {"hour": 1.67, "karma": 10}, {"hour": 2.67, "karma": 17}, {"hour": 3.67, "karma": 23}, {"hour": 4.67, "karma": 28}, {"hour": 5.67, "karma": 33}, {"hour": 6.0, "karma": 38}, {"hour": 6.16, "karma": 39}, {"hour": 6.67, "karma": 38}, {"hour": 7.67, "karma": 42}, {"hour": 8.67, "karma": 43}, {"hour": 9.67, "karma": 50}, {"hour": 10.67, "karma": 49}, {"hour": 11.67, "karma": 56}, {"hour": 12.67, "karma": 54}, {"hour": 13.67, "karma": 60}, {"hour": 14.67, "karma": 53}, {"hour": 15.67, "karma": 60}, {"hour": 16.67, "karma": 57}, {"hour": 17.67, "karma": 58}, {"hour": 18.67, "karma": 63}, {"hour": 19.67, "karma": 58}, {"hour": 20.67, "karma": 58}, {"hour": 21.67, "karma": 57}, {"hour": 22.67, "karma": 63}, {"hour": 23.67, "karma": 60}, {"hour": 24.67, "karma": 62}, {"hour": 25.67, "karma": 59}, {"hour": 26.67, "karma": 56}, {"hour": 27.67, "karma": 61}, {"hour": 28.67, "karma": 64}, {"hour": 29.67, "karma": 63}, {"hour": 30.67, "karma": 62}, {"hour": 31.67, "karma": 65}, {"hour": 32.67, "karma": 63}, {"hour": 33.67, "karma": 60}, {"hour": 34.67, "karma": 64}, {"hour": 35.67, "karma": 62}, {"hour": 36.67, "karma": 61}, {"hour": 37.67, "karma": 64}, {"hour": 38.67, "karma": 63}, {"hour": 39.67, "karma": 69}, {"hour": 40.67, "karma": 69}, {"hour": 41.67, "karma": 69}, {"hour": 42.67, "karma": 65}, {"hour": 43.67, "karma": 68}, {"hour": 44.67, "karma": 68}, {"hour": 45.67, "karma": 69}, {"hour": 46.67, "karma": 68}, {"hour": 47.67, "karma": 68}]}, {"mal_id": 59142, "progression": [{"hour": 0.87, "karma": 5}, {"hour": 1.87, "karma": 12}, {"hour": 2.87, "karma": 21}, {"hour": 3.87, "karma": 27}, {"hour": 4.87, "karma": 33}, {"hour": 5.87, "karma": 33}, {"hour": 6.2, "karma": 32}, {"hour": 6.36, "karma": 36}, {"hour": 6.87, "karma": 37}, {"hour": 7.87, "karma": 44}, {"hour": 8.87, "karma": 44}, {"hour": 9.87, "karma": 44}, {"hour": 10.87, "karma": 51}, {"hour": 11.87, "karma": 51}, {"hour": 12.87, "karma": 54}, {"hour": 13.87, "karma": 54}, {"hour": 14.87, "karma": 60}, {"hour": 15.87, "karma": 65}, {"hour": 16.87, "karma": 63}, {"hour": 17.87, "karma": 66}, {"hour": 18.87, "karma": 65}, {"hour": 19.87, "karma": 63}, {"hour": 20.87, "karma": 69}, {"hour": 21.87, "karma": 68}, {"hour": 22.87, "karma": 69}, {"hour": 23.87, "karma": 71}, {"hour": 24.87, "karma": 72}, {"hour": 25.87, "karma": 67}, {"hour": 26.87, "karma": 74}, {"hour": 27.87, "karma": 72}, {"hour": 28.87, "karma": 73}, {"hour": 29.87, "karma": 72}, {"hour": 30.87, "karma": 76}, {"hour": 31.87, "karma": 72}, {"hour": 32.87, "karma": 72}, {"hour": 33.87, "karma": 74}, {"hour": 34.87, "karma": 72}, {"hour": 35.87, "karma": 74}, {"hour": 36.87, "karma": 72}, {"hour": 37.87, "karma": 71}, {"hour": 38.87, "karma": 74}, {"hour": 39.87, "karma": 72}, {"hour": 40.87, "karma": 75}, {"hour": 41.87, "karma": 73}, {"hour": 42.87, "karma": 78}, {"hour": 43.87, "karma": 75}, {"hour": 44.87, "karma": 75}, {"hour": 45.87, "karma": 75}, {"hour": 46.87, "karma": 76}, {"hour": 47.87, "karma": 78}]}, {"mal_id": 55071, "progression": [{"hour": 0.97, "karma": 30}, {"hour": 1.97, "karma": 68}, {"hour": 2.97, "karma": 103}, {"hour": 3.97, "karma": 128}, {"hour": 4.97, "karma": 142}, {"hour": 5.97, "karma": 168}, {"hour": 6.3, "karma": 173}, {"hour": 6.46, "karma": 176}, {"hour": 6.97, "karma": 185}, {"hour": 7.97, "karma": 197}, {"hour": 8.97, "karma": 213}, {"hour": 9.97, "karma": 223}, {"hour": 10.97, "karma": 233}, {"hour": 11.97, "karma": 239}, {"hour": 12.97, "karma": 247}, {"hour": 13.97, "karma": 254}, {"hour": 14.97, "karma": 267}, {"hour": 15.97, "karma": 275}, {"hour": 16.97, "karma": 280}, {"hour": 17.97, "karma": 280}, {"hour": 18.97, "karma": 290}, {"hour": 19.97, "karma": 289}, {"hour": 20.97, "karma": 294}, {"hour": 21.97, "karma": 297}, {"hour": 22.97, "karma": 302}, {"hour": 23.97, "karma": 305}, {"hour": 24.97, "karma": 310}, {"hour": 25.97, "karma": 310}, {"hour": 26.97, "karma": 305}, {"hour": 27.97, "karma": 312}, {"hour": 28.97, "karma": 314}, {"hour": 29.97, "karma": 320}, {"hour": 30.97, "karma": 315}, {"hour": 31.97, "karma": 317}, {"hour": 32.97, "karma": 321}, {"hour": 33.97, "karma": 318}, {"hour": 34.97, "karma": 321}, {"hour": 35.97, "karma": 319}, {"hour": 36.97, "karma": 330}, {"hour": 37.97, "karma": 329}, {"hour": 38.97, "karma": 329}, {"hour": 39.97, "karma": 330}, {"hour": 40.97, "karma": 328}, {"hour": 41.97, "karma": 328}, {"hour": 42.97, "karma": 331}, {"hour": 43.97, "karma": 331}, {"hour": 44.97, "karma": 327}, {"hour": 45.97, "karma": 334}, {"hour": 46.97, "karma": 332}, {"hour": 47.97, "karma": 327}]}, {"mal_id": 59055, "progression": [{"hour": 0.17, "karma": 11}, {"hour": 1.17, "karma": 45}, {"hour": 2.17, "karma": 79}, {"hour": 3.17, "karma": 90}, {"hour": 3.51, "karma": 101}, {"hour": 3.66, "karma": 108}, {"hour": 4.17, "karma": 111}, {"hour": 5.17, "karma": 123}, {"hour": 6.17, "karma": 139}, {"hour": 7.17, "karma": 159}, {"hour": 8.17, "karma": 173}, {"hour": 9.17, "karma": 190}, {"hour": 10.17, "karma": 199}, {"hour": 11.17, "karma": 202}, {"hour": 12.17, "karma": 210}, {"hour": 13.17, "karma": 209}, {"hour": 14.17, "karma": 220}, {"hour": 15.17, "karma": 218}, {"hour": 16.17, "karma": 229}, {"hour": 17.17, "karma": 226}, {"hour": 18.17, "karma": 228}, {"hour": 19.17, "karma": 235}, {"hour": 20.17, "karma": 241}, {"hour": 21.17, "karma": 245}, {"hour": 22.17, "karma": 249}, {"hour": 23.17, "karma": 249}, {"hour": 24.17, "karma": 254}, {"hour": 25.17, "karma": 252}, {"hour": 26.17, "karma": 256}, {"hour": 27.17, "karma": 258}, {"hour": 28.17, "karma": 258}, {"hour": 29.17, "karma": 261}, {"hour": 30.17, "karma": 263}, {"hour": 31.17, "karma": 262}, {"hour": 32.17, "karma": 267}, {"hour": 33.17, "karma": 271}, {"hour": 34.17, "karma": 271}, {"hour": 35.17, "karma": 274}, {"hour": 36.17, "karma": 277}, {"hour": 37.17, "karma": 270}, {"hour": 38.17, "karma": 273}, {"hour": 39.17, "karma": 275}, {"hour": 40.17, "karma": 274}, {"hour": 41.17, "karma": 278}, {"hour": 42.17, "karma": 279}, {"hour": 43.17, "karma": 281}, {"hour": 44.17, "karma": 277}, {"hour": 45.17, "karma": 281}, {"hour": 46.17, "karma": 278}, {"hour": 47.17, "karma": 275}]}, {"mal_id": 58199, "progression": [{"hour": 0.47, "karma": 2}, {"hour": 1.47, "karma": 4}, {"hour": 2.47, "karma": 8}, {"hour": 3.47, "karma": 8}, {"hour": 4.47, "karma": 10}, {"hour": 5.47, "karma": 10}, {"hour": 6.47, "karma": 8}, {"hour": 7.47, "karma": 9}, {"hour": 8.47, "karma": 11}, {"hour": 9.47, "karma": 11}, {"hour": 10.47, "karma": 13}, {"hour": 11.47, "karma": 13}, {"hour": 12.47, "karma": 12}, {"hour": 13.47, "karma": 12}, {"hour": 14.47, "karma": 12}, {"hour": 15.47, "karma": 14}, {"hour": 16.47, "karma": 14}, {"hour": 17.47, "karma": 12}, {"hour": 18.47, "karma": 12}, {"hour": 19.47, "karma": 14}, {"hour": 20.47, "karma": 15}, {"hour": 21.47, "karma": 15}, {"hour": 22.47, "karma": 16}, {"hour": 23.47, "karma": 13}, {"hour": 24.47, "karma": 13}, {"hour": 25.47, "karma": 15}, {"hour": 26.47, "karma": 15}, {"hour": 27.47, "karma": 17}, {"hour": 28.47, "karma": 13}, {"hour": 29.47, "karma": 15}, {"hour": 30.47, "karma": 13}, {"hour": 31.47, "karma": 13}, {"hour": 32.47, "karma": 16}, {"hour": 33.47, "karma": 15}, {"hour": 34.47, "karma": 13}]}, {"mal_id": 54857, "progression": [{"hour": 0.47, "karma": 106}, {"hour": 1.47, "karma": 473}, {"hour": 2.47, "karma": 860}, {"hour": 3.47, "karma": 1158}, {"hour": 4.47, "karma": 1421}, {"hour": 5.47, "karma": 1676}, {"hour": 6.47, "karma": 1844}, {"hour": 7.47, "karma": 1974}, {"hour": 8.47, "karma": 2132}, {"hour": 9.47, "karma": 2280}, {"hour": 10.47, "karma": 2408}, {"hour": 11.47, "karma": 2508}, {"hour": 12.47, "karma": 2608}, {"hour": 13.47, "karma": 2695}, {"hour": 14.47, "karma": 2763}, {"hour": 15.47, "karma": 2820}, {"hour": 16.47, "karma": 2862}, {"hour": 17.47, "karma": 2906}, {"hour": 18.47, "karma": 2943}, {"hour": 19.47, "karma": 2968}, {"hour": 20.47, "karma": 3009}, {"hour": 21.47, "karma": 3037}, {"hour": 22.47, "karma": 3074}, {"hour": 23.47, "karma": 3092}, {"hour": 24.47, "karma": 3125}, {"hour": 25.47, "karma": 3141}, {"hour": 26.47, "karma": 3162}, {"hour": 27.47, "karma": 3172}, {"hour": 28.47, "karma": 3186}, {"hour": 29.47, "karma": 3212}, {"hour": 30.47, "karma": 3231}, {"hour": 31.47, "karma": 3253}]}, {"mal_id": 58484, "progression": [{"hour": 0.97, "karma": 19}, {"hour": 1.97, "karma": 38}, {"hour": 2.97, "karma": 69}, {"hour": 3.97, "karma": 86}, {"hour": 4.97, "karma": 106}, {"hour": 5.97, "karma": 121}, {"hour": 6.97, "karma": 137}, {"hour": 7.97, "karma": 148}, {"hour": 8.97, "karma": 166}, {"hour": 9.97, "karma": 173}, {"hour": 10.97, "karma": 182}, {"hour": 11.97, "karma": 184}, {"hour": 12.97, "karma": 190}, {"hour": 13.97, "karma": 202}, {"hour": 14.97, "karma": 208}, {"hour": 15.97, "karma": 213}, {"hour": 16.97, "karma": 212}, {"hour": 17.97, "karma": 217}, {"hour": 18.97, "karma": 217}, {"hour": 19.97, "karma": 221}, {"hour": 20.97, "karma": 225}, {"hour": 21.97, "karma": 228}, {"hour": 22.97, "karma": 228}, {"hour": 23.97, "karma": 231}, {"hour": 24.97, "karma": 234}, {"hour": 25.97, "karma": 236}, {"hour": 26.97, "karma": 231}, {"hour": 27.97, "karma": 232}, {"hour": 28.97, "karma": 239}, {"hour": 29.97, "karma": 238}, {"hour": 30.97, "karma": 242}, {"hour": 31.97, "karma": 243}]}, {"mal_id": 51119, "progression": [{"hour": 0.42, "karma": 1}, {"hour": 1.42, "karma": 3}, {"hour": 2.42, "karma": 8}, {"hour": 3.42, "karma": 17}, {"hour": 4.42, "karma": 19}, {"hour": 5.42, "karma": 22}, {"hour": 6.42, "karma": 22}, {"hour": 7.42, "karma": 22}, {"hour": 8.42, "karma": 22}, {"hour": 9.42, "karma": 26}, {"hour": 10.42, "karma": 33}, {"hour": 11.42, "karma": 28}, {"hour": 12.42, "karma": 33}, {"hour": 13.42, "karma": 38}, {"hour": 14.42, "karma": 32}, {"hour": 15.42, "karma": 38}, {"hour": 16.42, "karma": 37}, {"hour": 17.42, "karma": 34}, {"hour": 18.42, "karma": 33}, {"hour": 19.42, "karma": 39}, {"hour": 20.42, "karma": 41}, {"hour": 21.42, "karma": 43}, {"hour": 22.42, "karma": 40}, {"hour": 23.42, "karma": 39}, {"hour": 24.42, "karma": 41}, {"hour": 25.42, "karma": 40}, {"hour": 26.42, "karma": 41}, {"hour": 27.42, "karma": 43}, {"hour": 28.42, "karma": 40}, {"hour": 29.42, "karma": 42}, {"hour": 30.42, "karma": 41}]}, {"mal_id": 58822, "progression": [{"hour": 0.97, "karma": 17}, {"hour": 1.97, "karma": 26}, {"hour": 2.97, "karma": 39}, {"hour": 3.97, "karma": 47}, {"hour": 4.97, "karma": 62}, {"hour": 5.97, "karma": 73}, {"hour": 6.97, "karma": 84}, {"hour": 7.97, "karma": 95}, {"hour": 8.97, "karma": 102}, {"hour": 9.97, "karma": 115}, {"hour": 10.97, "karma": 123}, {"hour": 11.97, "karma": 127}, {"hour": 12.97, "karma": 133}, {"hour": 13.97, "karma": 138}, {"hour": 14.97, "karma": 144}, {"hour": 15.97, "karma": 149}, {"hour": 16.97, "karma": 153}, {"hour": 17.97, "karma": 146}, {"hour": 18.97, "karma": 154}, {"hour": 19.97, "karma": 154}, {"hour": 20.97, "karma": 158}, {"hour": 21.97, "karma": 164}, {"hour": 22.97, "karma": 165}, {"hour": 23.97, "karma": 165}, {"hour": 24.97, "karma": 165}, {"hour": 25.97, "karma": 166}, {"hour": 26.97, "karma": 166}, {"hour": 27.97, "karma": 171}, {"hour": 28.97, "karma": 168}, {"hour": 29.97, "karma": 172}, {"hour": 30.97, "karma": 175}]}, {"mal_id": 59265, "progression": [{"hour": 0.92, "karma": 9}, {"hour": 1.92, "karma": 14}, {"hour": 2.93, "karma": 31}, {"hour": 3.92, "karma": 44}, {"hour": 4.93, "karma": 45}, {"hour": 5.92, "karma": 59}, {"hour": 6.92, "karma": 75}, {"hour": 7.92, "karma": 86}, {"hour": 8.93, "karma": 87}, {"hour": 9.92, "karma": 99}, {"hour": 10.92, "karma": 101}, {"hour": 11.92, "karma": 106}, {"hour": 12.92, "karma": 119}, {"hour": 13.92, "karma": 119}, {"hour": 14.92, "karma": 123}, {"hour": 15.93, "karma": 130}, {"hour": 16.92, "karma": 130}, {"hour": 17.92, "karma": 133}, {"hour": 18.92, "karma": 131}, {"hour": 19.93, "karma": 128}, {"hour": 20.92, "karma": 132}, {"hour": 21.93, "karma": 134}, {"hour": 22.92, "karma": 138}, {"hour": 23.92, "karma": 141}, {"hour": 24.92, "karma": 134}, {"hour": 25.92, "karma": 137}, {"hour": 26.92, "karma": 137}, {"hour": 27.92, "karma": 136}, {"hour": 28.92, "karma": 139}, {"hour": 29.92, "karma": 141}]}, {"mal_id": 58271, "progression": [{"hour": 0.97, "karma": 30}, {"hour": 1.97, "karma": 57}, {"hour": 2.97, "karma": 81}, {"hour": 3.97, "karma": 89}, {"hour": 4.97, "karma": 100}, {"hour": 5.97, "karma": 115}, {"hour": 6.97, "karma": 129}, {"hour": 7.97, "karma": 151}, {"hour": 8.97, "karma": 163}, {"hour": 9.97, "karma": 166}, {"hour": 10.97, "karma": 172}, {"hour": 11.97, "karma": 184}, {"hour": 12.97, "karma": 187}, {"hour": 13.97, "karma": 188}, {"hour": 14.97, "karma": 194}, {"hour": 15.97, "karma": 198}, {"hour": 16.97, "karma": 205}, {"hour": 17.97, "karma": 204}, {"hour": 18.97, "karma": 206}, {"hour": 19.97, "karma": 212}, {"hour": 20.97, "karma": 217}, {"hour": 21.97, "karma": 218}, {"hour": 22.97, "karma": 216}, {"hour": 23.97, "karma": 221}, {"hour": 24.97, "karma": 227}, {"hour": 25.97, "karma": 226}, {"hour": 26.97, "karma": 230}, {"hour": 27.97, "karma": 226}, {"hour": 28.97, "karma": 234}]}, {"mal_id": 59561, "progression": [{"hour": 0.47, "karma": 4}, {"hour": 1.47, "karma": 11}, {"hour": 2.47, "karma": 20}, {"hour": 3.47, "karma": 37}, {"hour": 4.47, "karma": 49}, {"hour": 5.47, "karma": 58}, {"hour": 6.47, "karma": 65}, {"hour": 7.47, "karma": 80}, {"hour": 8.47, "karma": 84}, {"hour": 9.47, "karma": 102}]}, {"mal_id": 56653, "progression": [{"hour": 0.46, "karma": 31}, {"hour": 1.46, "karma": 96}, {"hour": 2.46, "karma": 151}, {"hour": 3.46, "karma": 198}, {"hour": 4.46, "karma": 233}, {"hour": 5.46, "karma": 265}, {"hour": 6.46, "karma": 288}, {"hour": 7.46, "karma": 317}]}, {"mal_id": 59144, "progression": [{"hour": 0.46, "karma": 3}, {"hour": 1.46, "karma": 5}, {"hour": 2.46, "karma": 12}, {"hour": 3.46, "karma": 12}, {"hour": 4.46, "karma": 15}, {"hour": 5.46, "karma": 21}, {"hour": 6.46, "karma": 20}, {"hour": 7.46, "karma": 26}]}, {"mal_id": 57592, "progression": [{"hour": 0.93, "karma": 40}, {"hour": 1.93, "karma": 85}, {"hour": 2.93, "karma": 134}, {"hour": 3.93, "karma": 193}, {"hour": 4.93, "karma": 247}, {"hour": 5.93, "karma": 283}, {"hour": 6.93, "karma": 345}, {"hour": 7.93, "karma": 388}]}, {"mal_id": 57719, "progression": [{"hour": 0.86, "karma": 39}, {"hour": 1.86, "karma": 87}, {"hour": 2.86, "karma": 115}, {"hour": 3.86, "karma": 142}, {"hour": 4.86, "karma": 174}, {"hour": 5.86, "karma": 199}]}, {"mal_id": 58739, "progression": [{"hour": 0.86, "karma": 8}, {"hour": 1.86, "karma": 20}, {"hour": 2.86, "karma": 34}, {"hour": 3.86, "karma": 39}, {"hour": 4.86, "karma": 46}, {"hour": 5.86, "karma": 44}]}, {"mal_id": 54769, "progression": [{"hour": 0.97, "karma": 1}, {"hour": 1.97, "karma": 1}, {"hour": 2.97, "karma": 3}, {"hour": 3.97, "karma": 1}, {"hour": 4.97, "karma": 0}, {"hour": 5.97, "karma": 4}]}, {"mal_id": 58259, "progression": [{"hour": 0.96, "karma": 6}, {"hour": 1.96, "karma": 8}, {"hour": 2.96, "karma": 10}, {"hour": 3.96, "karma": 13}, {"hour": 4.96, "karma": 17}]}, {"mal_id": 57554, "progression": [{"hour": 0.86, "karma": 13}, {"hour": 1.86, "karma": 27}, {"hour": 2.86, "karma": 38}, {"hour": 3.86, "karma": 49}]}]